<?xml version="1.0" encoding="UTF-8" standalone="yes" ?> 
<DATAPACKET Version="2.0">
<METADATA>
	<FIELDS>
		<FIELD attrname="A" fieldtype="r8" desc="Código" /> 
		<FIELD attrname="B" fieldtype="string" WIDTH="60" desc="Descripción" /> 
	</FIELDS>
	<PARAMS LCID="1034" /> 
</METADATA>
<ROWDATA>
<ROW A="3" B="SEXO" />
<ROW A="4" B="SECCION" />
<ROW A="5" B="FECHA DE NACIMIENTO" />
<ROW A="6" B="NRO. DE POLIZA" />
<ROW A="13" B="TIPO DE CARGA" />
<ROW A="14" B="USO DEL VEHICULO" />
<ROW A="15" B="GRUPO DEL VEHICULO" />
<ROW A="16" B="TIPO DE VEHICULO" />
<ROW A="17" B="ORIGEN DEL VEHICULO" />
<ROW A="18" B="FECHA DE REGISTRO" />
<ROW A="19" B="CARGA O PASAJEROS" />
<ROW A="20" B="CARGA MAXIMA" />
<ROW A="21" B="MODELO DEL VEHICULO" />
<ROW A="30" B="LOCALIDAD" />
<ROW A="31" B="CODIGO POSTAL" />
<ROW A="32" B="ULTIMO CONTACTO" />
<ROW A="33" B="SINIESTROS SIMILARES ANT." />
<ROW A="34" B="HECHOS SIMILARES EN LA ZONA" />
<ROW A="35" B="NOMBRE CAUSANTE DIRECTO" />
<ROW A="36" B="DOMICILIO DEL CAUSANTE" />
<ROW A="37" B="RELACION C/ASEGURADO" />
<ROW A="38" B="?EXISTE CULPABILIDAD?" />
<ROW A="39" B="RAZON" />
<ROW A="40" B="DAÑO CAUSADO POR EXIGENCIA DEL TRABAJO?" />
<ROW A="41" B="?HA SIDO PREVISTO?" />
<ROW A="42" B="?INDEP. DE LA VOLUNTAD DE QUIEN LO CAUSO?" />
<ROW A="43" B="MEDIDAS PARA EVITAR OTROS DA?OS" />
<ROW A="44" B="OBJETO DETERIORADO" />
<ROW A="45" B="RAZON SOCIAL" />
<ROW A="46" B="PERIODO FACTURADO" />
<ROW A="50" B="BENEF-1  NO DECLARADO EN POL" />
<ROW A="55" B="TIPO DOC. BENEF-1" />
<ROW A="58" B="NRO. DOC. BENEF-1" />
<ROW A="60" B="BENEF-2  NO DECLARADO EN POL" />
<ROW A="65" B="TIPO DOC. BENEF-2" />
<ROW A="68" B="NRO. DOC. BENEF-2" />
<ROW A="70" B="BENEF-3  NO DECLARADO EN POL" />
<ROW A="75" B="TIPO DOC. BENEF-3" />
<ROW A="78" B="NRO. DOC. BENEF-3" />
<ROW A="100" B="COLOR DE OJOS" />
<ROW A="110" B="DESCRIPTIVO BREVE" />
<ROW A="111" B="DISCOVERER_GRAL" />
<ROW A="200" B="MOTIVO DE OBS. EN POLIZA" />
<ROW A="201" B="APLICA POLIZAS RELACIONADAS" />
<ROW A="202" B="TRANSFERIR EN RENOVACION" />
<ROW A="210" B="MOTIVO DE OBS. CLIENTE" />
<ROW A="250" B="INDICADOR DE OBS. EN POLIZA" />
<ROW A="260" B="SIGLA COMPORTAMIENTO OBS. CLIENTE" />
<ROW A="360" B="TIPO BIEN" />
<ROW A="365" B="MARCA" />
<ROW A="370" B="TIPO-MARCA" />
<ROW A="5000" B="Monto Perdidas y/o Daños" />
<ROW A="5001" B="Limite asegurado" />
<ROW A="5002" B="Valor a Riesgo" />
<ROW A="5003" B="% Asegurado" />
<ROW A="5004" B="% Infraseguro" />
<ROW A="5005" B="Quitas" />
<ROW A="5006" B="Detalle Quitas" />
<ROW A="5007" B="Franquicia" />
<ROW A="5008" B="Otros (importe)" />
<ROW A="5009" B="Detallar Otros" />
<ROW A="5010" B="Monto Indemnizacion" />
<ROW A="5011" B="Observaciones" />
<ROW A="5012" B="Monto Indem. en Especie" />
<ROW A="5013" B="Prestador" />
<ROW A="5020" B="Monto rep. Daños" />
<ROW A="5021" B="Monto Limite" />
<ROW A="5022" B="Monto Indemnizar" />
<ROW A="5023" B="Observaciones" />
<ROW A="5024" B="Monto Indem. en Especie" />
<ROW A="5025" B="Prestador" />
<ROW A="5030" B="Monto reclamado" />
<ROW A="5031" B="Monto verificado" />
<ROW A="5032" B="Monto Limite" />
<ROW A="5033" B="Franquicia" />
<ROW A="5034" B="Quitas" />
<ROW A="5035" B="Detallar Quitas" />
<ROW A="5036" B="Monto a Indemnizar" />
<ROW A="5037" B="Observaciones" />
<ROW A="5040" B="Monto reclamado" />
<ROW A="5041" B="Monto verificado" />
<ROW A="5042" B="Monto limite" />
<ROW A="5043" B="Quitas" />
<ROW A="5044" B="Detallar Quitas" />
<ROW A="5045" B="Monto a Indemnizar" />
<ROW A="5046" B="Observaciones" />
<ROW A="5047" B="Monto Indem. en Especie" />
<ROW A="5048" B="Prestador" />
<ROW A="5049" B="Otros (importe)" />
<ROW A="5050" B="Detallar Otros" />
<ROW A="10001" B="DESTINO" />
<ROW A="10002" B="RECONSTRUCCION Y/O REPARACION Y/O REPOSICION" />
<ROW A="10003" B="CLAUSULA SWING" />
<ROW A="10004" B="CLAUSULA 72 HS" />
<ROW A="10005" B="CLAUSULA INSTALACIONES ELECTRICAS" />
<ROW A="10006" B="DEDUCIBLES SUBLIMITES" />
<ROW A="10007" B="PERIODO DE INDEMNIZACION" />
<ROW A="10008" B="FRANQUICIA" />
<ROW A="10009" B="DEDUCIBLE GENERAL" />
<ROW A="10010" B="UBICACION" />
<ROW A="10011" B="INTERRUPCION DE ACCESOS" />
<ROW A="10012" B="DEDUCIBLE" />
<ROW A="10013" B="DEDUCIBLE" />
<ROW A="10014" B="RESPONSABILIDAD CIVIL CRUZADA" />
<ROW A="10015" B="ZONA GEOGRAFICA" />
<ROW A="10016" B="CLAUS ESTABILIZ SUMA ASEG" />
<ROW A="10017" B="DEMAS SUBJETIVIDADES SUBLIMITES" />
<ROW A="10018" B="ANTIGÜEDAD DEL EDIFICIO" />
<ROW A="10019" B="REGIMEN DE OCUPACION" />
<ROW A="10020" B="TIPO DE TECHOS" />
<ROW A="10021" B="PILETA DE NATACION" />
<ROW A="10022" B="FRANQUICIA RESPONSABILIAD CIVIL" />
<ROW A="10023" B="SERVICIO SOS DE ASISTENCIA" />
<ROW A="10024" B="CLAUSULA DAÑOS ELECTRICOS" />
<ROW A="10100" B="NUMERO DE PISOS" />
<ROW A="10500" B="EQUIPOS ELECTRONICOS" />
<ROW A="10510" B="CRISTALES" />
<ROW A="10520" B="REMOCION DE ESCOMBROS" />
<ROW A="10530" B="GASTOS EXTRAORDINARIOS" />
<ROW A="10540" B="RECONSTRUCCION DE DOCUMENTOS" />
<ROW A="10550" B="INCORPORACION AUTOM. DE BIENES" />
<ROW A="10560" B="COMBUSTION ESPONTANEA" />
<ROW A="10570" B="GASTOS VARIOS Y/O FLETES" />
<ROW A="10580" B="DAÑOS POR AGUA" />
<ROW A="10590" B="CONSTRUCCION Y MONTAJE" />
<ROW A="10591" B="GASTOS DE ACELERACION" />
<ROW A="10592" B="INUNDACION" />
<ROW A="10593" B="FALTA DE FRIO" />
<ROW A="10594" B="ROBO CONTENIDO GENERAL" />
<ROW A="10595" B="ROBO DE VALORES EN CAJA" />
<ROW A="10596" B="ROBO EN TRANSITO" />
<ROW A="10597" B="HONORARIOS PROFESIONALES" />
<ROW A="10600" B="GRANIZO" />
<ROW A="10610" B="H.V.C.T." />
<ROW A="10620" B="TERREMOTO-INCENDIO" />
<ROW A="10630" B="TERREMOTO-DAÑOS" />
<ROW A="10700" B="DISYUNTOR" />
<ROW A="10710" B="CLAUSULA DE DERRUMBE" />
<ROW A="10750" B="PERIODO DE INDEMNIZACION - PERDIDA DE BENEFICIOS" />
<ROW A="10800" B="TIPO DE EDIFICIO" />
<ROW A="10850" B="EXT. INCENDIO EDIFICIO A PARTES PROPIAS" />
<ROW A="10855" B="DAÑOS POR TENSION" />
<ROW A="10900" B="ZONA GEOGRAFICA" />
<ROW A="11000" B="RC CARTELES, LETREROS Y MARQUESINAS" />
<ROW A="11100" B="RC, INC, RAYO Y/O EXPLOSION" />
<ROW A="11200" B="RC, PILETAS DE NATACION" />
<ROW A="11300" B="COBERTURA DE ACCID. PERS." />
<ROW A="11400" B="CANTIDAD DE PISOS" />
<ROW A="11500" B="CANTIDAD DE ASCENSORES" />
<ROW A="11501" B="NUMERO DE ASCENSORES" />
<ROW A="11502" B="NUMERO DE CALDERAS" />
<ROW A="11600" B="MEJORAS" />
<ROW A="12000" B="MOTOCICLETA" />
<ROW A="12500" B="RAMPA, AUTOELEV." />
<ROW A="12550" B="ROTURA DE CAÑERIAS" />
<ROW A="12560" B="METROS CUADRADOS CUBIERTOS" />
<ROW A="12570" B="RECONSTRUCCION A NUEVO" />
<ROW A="12580" B="CALIDAD DE CONSTRUCCION" />
<ROW A="13000" B="CANTIDAD DE BOLSAS SILO" />
<ROW A="13100" B="ZONA DE RIESGO" />
<ROW A="13200" B="DISTANCIA CURSO DE AGUA" />
<ROW A="13300" B="CAPACIDAD MAXIMO POR BOLSA" />
<ROW A="13400" B="SEMILLA" />
<ROW A="13500" B="INUNDACION" />
<ROW A="13550" B="REGION" />
<ROW A="13560" B="ESPECIES" />
<ROW A="13570" B="CANTIDAD DE HECTAREAS" />
<ROW A="13580" B="H.V.C.T. PLANTACIONES FORESTALES" />
<ROW A="13590" B="GRANIZO PLANTACIONES FORESTALES" />
<ROW A="13600" B="INUNDACION PLANTACIONES FORESTALES" />
<ROW A="13610" B="TERREMOTO PLANTACIONES FORESTALES" />
<ROW A="14000" B="CANTIDAD DE EDIFICIOS PROPIEDAD DEL COUNTRIE" />
<ROW A="15000" B="RC COMPRENSIVA - ADIC. INC.,RAYO, EXPLOSIÓN, DESCARGA ELECTR" />
<ROW A="15005" B="RC COMPRENSIVA - ADIC.  CARTELES, LETREROS Y MARQUESINAS" />
<ROW A="15010" B="RC COMPRENSIVA - ADIC. SUMINISTRO DE ALIMENTOS" />
<ROW A="15020" B="RC COMPRENSIVA - ADIC. USO DE ARMAS DE FUEGO" />
<ROW A="15030" B="RC COMPRENSIVA - ADIC. ASCENSORES Y MONTACARGAS" />
<ROW A="15040" B="RC COMPRENSIVA - ADIC. CALDERAS" />
<ROW A="15050" B="RC COMPRENSIVA - ADIC. VENDEDORES AMBULANTES Y/O VIAJANTES" />
<ROW A="15060" B="RC COMPRENSIVA - ADIC. CONTRATISTAS Y/O SUBCONTRATISTAS" />
<ROW A="15070" B="RC COMPRENSIVA - ADIC. GUARDA Y/O DEPOSITO DE VEHICULOS" />
<ROW A="15080" B="RC COMPRENSIVA - ADIC. DAÑOS BBCC" />
<ROW A="15085" B="RC COMPRENSIVA - ADIC. CARGA Y DESCARGA" />
<ROW A="15090" B="RC COMPRENSIVA - ADIC. CRUZADA" />
<ROW A="15095" B="RC COMPRENSIVA - ADIC. GRUAS, GUINCHES Y AUTO." />
<ROW A="15100" B="INST. CONTRA INCENDIO" />
<ROW A="15110" B="PROTECCION ELECTRICA" />
<ROW A="15120" B="DEDUCIBLE LIM. 2" />
<ROW A="15200" B="SUB-LIMITE 3" />
<ROW A="15210" B="MTO-LIMITE 3" />
<ROW A="15220" B="DEDUCIBLE LIM. 3" />
<ROW A="15300" B="SUB-LIMITE 4" />
<ROW A="15310" B="MTO-LIMITE 4" />
<ROW A="15320" B="DEDUCIBLE LIM. 4" />
<ROW A="15400" B="SUB-LIMITE 5" />
<ROW A="15410" B="MTO-LIMITE 5" />
<ROW A="15420" B="DEDUCIBLE LIM. 5" />
<ROW A="15500" B="SUB-LIMITE 6" />
<ROW A="15510" B="MTO-LIMITE 6" />
<ROW A="15520" B="DEDUCIBLE LIM. 6" />
<ROW A="15600" B="SUB-LIMITE 7" />
<ROW A="15610" B="MTO-LIMITE 7" />
<ROW A="15620" B="DEDUCIBLE LIM. 7" />
<ROW A="15700" B="SUB-LIMITE 8" />
<ROW A="15710" B="MTO-LIMITE 8" />
<ROW A="15720" B="DEDUCIBLE LIM. 8" />
<ROW A="15800" B="SUB-LIMITE 9" />
<ROW A="15810" B="MTO-LIMITE 9" />
<ROW A="15820" B="DEDUCIBLE LIM. 9" />
<ROW A="15900" B="SUB-LIMITE 10" />
<ROW A="15910" B="MTO-LIMITE 10" />
<ROW A="15920" B="DEDUCIBLE LIM. 10" />
<ROW A="16000" B="SUB-LIMITE 11" />
<ROW A="16010" B="MTO-LIMITE 11" />
<ROW A="16020" B="DEDUCIBLE LIM. 11" />
<ROW A="16100" B="SUB-LIMITE 12" />
<ROW A="16110" B="MTO-LIMITE 12" />
<ROW A="16120" B="DEDUCIBLE LIM. 12" />
<ROW A="16200" B="SUB-LIMITE 13" />
<ROW A="16210" B="MTO-LIMITE 13" />
<ROW A="16220" B="DEDUCIBLE LIM. 13" />
<ROW A="16300" B="SUB-LIMITE 14" />
<ROW A="16310" B="MTO-LIMITE 14" />
<ROW A="16320" B="DEDUCIBLE LIM. 14" />
<ROW A="16400" B="SUB-LIMITE 15" />
<ROW A="16410" B="MTO-LIMITE 15" />
<ROW A="16420" B="DEDUCIBLE LIM. 15" />
<ROW A="17000" B="DEDUCIBLE GENERAL" />
<ROW A="17500" B="CANTIDAD DE MODULOS" />
<ROW A="18000" B="TIPO DE CONSTRUCCION EXTERIOR" />
<ROW A="18001" B="TIPO DE TECHOS" />
<ROW A="19000" B="HVCT" />
<ROW A="19005" B="GRANIZO" />
<ROW A="19007" B="PROTECCION ELECTRICA" />
<ROW A="19008" B="INSTALACIONES CONTRA INCENDIO" />
<ROW A="19009" B="CERRAMIENTO PERIMETRAL" />
<ROW A="19010" B="SEGURIDAD Y SERENO" />
<ROW A="19011" B="ALARMA CONTRA ROBO" />
<ROW A="19012" B="CAMARAS DE VIDEO" />
<ROW A="19013" B="FRANQUICIA PARA VALORES" />
<ROW A="19014" B="DAÑOS POR TENSION" />
<ROW A="19015" B="CALZADAS Y ACERAS" />
<ROW A="19016" B="R.C. ACTIVIDADES DEPORTIVAS" />
<ROW A="19017" B="R.C. CAIDA DE ARBOLES" />
<ROW A="19018" B="R.C. SUMINISTRO DE ALIMENTOS" />
<ROW A="19019" B="R.C. CONTRATISTAS Y SUBCONTRATISTAS" />
<ROW A="19020" B="R.C. ANIMALES DOMESTICOS" />
<ROW A="19021" B="CANTIDAD DE CALDERAS" />
<ROW A="19022" B="CANTIDAD DE ASCENSORES" />
<ROW A="19023" B="USO DE ARMAS DE FUEGO" />
<ROW A="19024" B="R.C. CRUZADA" />
<ROW A="19025" B="R.C. CARGA Y DESCARGA" />
<ROW A="19026" B="R.C. EVENTOS ARTISTICOS Y/O RECREATIVOS" />
<ROW A="19027" B="R.C. ANTENAS, MASTILES Y/U OBJETOS AFINES" />
<ROW A="19028" B="R.C. PELOTEROS Y OTROS JUEGOS" />
<ROW A="19029" B="R.C. EXCURSIONES" />
<ROW A="19030" B="R.C. GRUAS, GUINCHES Y AUTOELEVADORES" />
<ROW A="20001" B="LUGAR PUERTO DE EMBARQUE" />
<ROW A="20002" B="FALTA DE ENTREGA" />
<ROW A="20003" B="GUERRA Y HUELGA" />
<ROW A="20004" B="ESTADIA EN ADUANA" />
<ROW A="20005" B="TRANSBORDOS" />
<ROW A="20006" B="EXTENSION VIAJES TERRESTRES" />
<ROW A="20007" B="TRANSPORTE SOBRE CUBIERTA" />
<ROW A="20008" B="NOMBRE DE LA EMBARCACION" />
<ROW A="20020" B="% DE MERCADERIA 1" />
<ROW A="20025" B="MATRICULA CON DESCUENTO COMERCIAL" />
<ROW A="20030" B="% DE MERCADERIA 2" />
<ROW A="20039" B="TIPO DE VEHICULO" />
<ROW A="20040" B="% TIPO DE VEHICULO 1" />
<ROW A="20045" B="TIPO DE VEHICULO 1" />
<ROW A="20050" B="% TIPO DE VEHICULO 2" />
<ROW A="20055" B="TIPO DE VEHICULO 2" />
<ROW A="20060" B="% TIPO DE VEHICULO 3" />
<ROW A="20065" B="TIPO DE VEHICULO 3" />
<ROW A="20070" B="% CLASE DE MERCADERIA A" />
<ROW A="20080" B="% CLASE DE MERCADERIA B" />
<ROW A="20090" B="DISTANCIA" />
<ROW A="20095" B="DISTANCIA INTERNACIONAL" />
<ROW A="20100" B="PORCENTAJE" />
<ROW A="20110" B="PORCENTAJE DE FRANQUICIA" />
<ROW A="20120" B="TABLA TRANSPORTE" />
<ROW A="20121" B="TM1. TIPO DE MERCADERIA 1" />
<ROW A="20122" B="TM2. TIPO DE MERCADERIA 2" />
<ROW A="20123" B="TV1. TIPO DE VEHICULO 1" />
<ROW A="20124" B="TV2. TIPO DE VEHICULO 2" />
<ROW A="20125" B="TV3. TIPO DE VEHICULO 3" />
<ROW A="20126" B="CLASE DE MERCADERIA A" />
<ROW A="20127" B="CLASE DE MERCADERIA B" />
<ROW A="20128" B="MEDIO DE TRANSPORTE" />
<ROW A="20129" B="MERCADERIA TIPO" />
<ROW A="20130" B="MERCADERIA CLASE" />
<ROW A="20131" B="TIPO DE VEHICULO" />
<ROW A="20200" B="EXENCION DE RESP TPTISTA." />
<ROW A="20300" B="DESCOMPOSTURA MAQ FRIG." />
<ROW A="20400" B="QUIEN Y DONDE SE TRANSPORTAN" />
<ROW A="20410" B="ESTADIA EN ADUANA" />
<ROW A="20500" B="MERCADERIAS" />
<ROW A="20510" B="MERCADERIA PERMITIDA EN SELF" />
<ROW A="20520" B="TIPO DE MERCADERIA" />
<ROW A="20525" B="OBJETO DE SEGURO" />
<ROW A="20530" B="MODULO SUMA ASEGURADA" />
<ROW A="20540" B="AMBITO DE COBERTURA" />
<ROW A="20600" B="NRO. DE GUIA" />
<ROW A="20700" B="LINEAS AEREAS" />
<ROW A="20800" B="CANTIDAD DE EQUIPOS" />
<ROW A="20900" B="TIPO DE ENDOSO" />
<ROW A="20950" B="G.P.S." />
<ROW A="21000" B="FRANQUICIA ROBO" />
<ROW A="21050" B="DEDUCIBLE ROBO" />
<ROW A="21100" B="CATEG. DE MERCADERIA" />
<ROW A="21200" B="ZONA DE RIESGO" />
<ROW A="21300" B="TRANSP. DESDE-HASTA" />
<ROW A="21400" B="FRANQUICIA OTROS EVENTOS" />
<ROW A="21500" B="MEDIDAS DE SEGURIDAD" />
<ROW A="21600" B="CUIT EMPRESA TRANSPORTISTA" />
<ROW A="21700" B="LUGAR DE PARTIDA" />
<ROW A="21800" B="LUGAR DE LLEGADA" />
<ROW A="21900" B="MOV.ESTIMADO ANUAL" />
<ROW A="22000" B="LOGISTICA / GERENCIAMIENTO" />
<ROW A="22100" B="BUEN RESULTADO" />
<ROW A="22200" B="NRO COBERTURA SELF" />
<ROW A="22300" B="CANTIDAD DE VIAJES" />
<ROW A="22400" B="PATENTE TRACTOR" />
<ROW A="22450" B="PATENTE CAMION" />
<ROW A="22500" B="PATENTE ACOPL./SEMI 1" />
<ROW A="22600" B="PATENTE ACOPL./SEMI 2" />
<ROW A="22700" B="PATENTE ACOPL/SEMI  3" />
<ROW A="23010" B="PERIODO DE INDEMNIZACION" />
<ROW A="30000" B="NRO. DE MATRICULA" />
<ROW A="30100" B="TIPO DE AERONAVE" />
<ROW A="35000" B="EXCLUSION DE RC" />
<ROW A="35100" B="CANTIDAD DE PLAZAS" />
<ROW A="35200" B="PATENTE" />
<ROW A="36000" B="RANGO DE EDAD" />
<ROW A="36001" B="GRUPO ETARIO" />
<ROW A="36010" B="AMBITO IQA" />
<ROW A="36011" B="AMBITO IQB" />
<ROW A="36401" B="MESES COBERTURA DROG. ONC." />
<ROW A="36701" B="RDI RETROACTIVA" />
<ROW A="36702" B="RDI DIAS DE ESPERA" />
<ROW A="36703" B="RDI CAUSA" />
<ROW A="36704" B="AMBITO RDI" />
<ROW A="36705" B="MESES COBERTURA RDI" />
<ROW A="36706" B="IRN RETROACTIVA" />
<ROW A="36707" B="IRN DIAS DE ESPERA" />
<ROW A="36708" B="CP RETROACTIVA" />
<ROW A="36709" B="CP BENEF MAX" />
<ROW A="36710" B="CP CAUSA" />
<ROW A="36711" B="NOMBRE ASEGURADO 1" />
<ROW A="36712" B="FE. NAC. ASEGURADO 1" />
<ROW A="36713" B="CUIL ASEGURADO 1" />
<ROW A="36714" B="NOMBRE ASEGURADO 2" />
<ROW A="36715" B="FE. NAC. ASEGURADO 2" />
<ROW A="36716" B="CUIL ASEGURADO 2" />
<ROW A="36717" B="PERSONAS CUBIERTAS :" />
<ROW A="36718" B="NOMBRE ASEGURADO 3" />
<ROW A="36719" B="FE. NAC. ASEGURADO 3" />
<ROW A="36720" B="CUIL ASEGURADO 3" />
<ROW A="36721" B="NOMBRE ASEGURADO 4" />
<ROW A="36722" B="FE. NAC. ASEGURADO 4" />
<ROW A="36723" B="CUIL ASEGURADO 4" />
<ROW A="40001" B="FABRICACION" />
<ROW A="40002" B="TIPO DE CARROCERIA (INFO)" />
<ROW A="40003" B="MOTOR" />
<ROW A="40004" B="AÑO" />
<ROW A="40005" B="NRO CHASIS" />
<ROW A="40006" B="PATENTE" />
<ROW A="40007" B="BUEN RESULTADO" />
<ROW A="40008" B="TIPO DE CARROCERIA" />
<ROW A="40010" B="MARCA" />
<ROW A="40011" B="BONIFICACION BUEN RESULTADO" />
<ROW A="40015" B="SERVICIO PETROLERO Y/O MINERO" />
<ROW A="40020" B="MODELO" />
<ROW A="40030" B="ZONA DE RIESGO" />
<ROW A="40035" B="VEHICULOS" />
<ROW A="40036" B="TARIFACION" />
<ROW A="40037" B="VEHICULOS(SSN)" />
<ROW A="40038" B="VEH.SSN (RES.24874)" />
<ROW A="40039" B="VEH.SSN (RES.22240)" />
<ROW A="40040" B="TIPO DE VEHICULO" />
<ROW A="40043" B="CARACTERISTICA 1" />
<ROW A="40044" B="CARACTERISTICA 2" />
<ROW A="40045" B="CARACTERISTICA 3" />
<ROW A="40046" B="AJUSTE CARACTERISTICAS" />
<ROW A="40048" B="NRO. RUTA" />
<ROW A="40050" B="TIPO DE CLIENTE" />
<ROW A="40055" B="ALCANCE" />
<ROW A="40060" B="JURISDICCION" />
<ROW A="40065" B="TIPO DE SERVICIO" />
<ROW A="40070" B="NRO MOTOR" />
<ROW A="40080" B="USO VEHICULO (SSN)" />
<ROW A="40081" B="DESTINO" />
<ROW A="40082" B="TIPO DE CARGA" />
<ROW A="40090" B="PROVINCIA" />
<ROW A="40095" B="VOLCADOR" />
<ROW A="40100" B="CLIENTE NUEVO" />
<ROW A="40200" B="VEHICULOS UIF" />
<ROW A="41000" B="NOMBRE DEL CONDUCTOR" />
<ROW A="41010" B="EDAD CONDUCTOR" />
<ROW A="41020" B="DOMICILIO CONDUCTOR" />
<ROW A="41030" B="NRO. REGISTRO DE CONDUCIR" />
<ROW A="41031" B="NRO. DE CONTROL" />
<ROW A="41035" B="DESC. CATEG. REGISTRO" />
<ROW A="41041" B="VIGENCIA DESDE" />
<ROW A="41042" B="VIGENCIA HASTA" />
<ROW A="41050" B="EXPEDIDO POR:" />
<ROW A="41060" B="GENERO" />
<ROW A="41070" B="ESTADO CIVIL" />
<ROW A="41080" B="HABITUALIDAD" />
<ROW A="41090" B="LUGAR" />
<ROW A="41100" B="RADIO ACCION" />
<ROW A="41110" B="ALCANCE" />
<ROW A="41120" B="NOMBRE PROPIETARIO" />
<ROW A="41130" B="DOMICILIO PROPIETARIO" />
<ROW A="41140" B="TIPO DE LESIONADO" />
<ROW A="41150" B="TIPO DE LESION" />
<ROW A="41155" B="MARCA - MODELO" />
<ROW A="41158" B="PATENTE-TERC." />
<ROW A="41160" B="COLOR VEHICULO" />
<ROW A="41170" B="VARIACION POR ROBO" />
<ROW A="41175" B="AUTOS-FP" />
<ROW A="41180" B="DESCUENTO 0 KM." />
<ROW A="41190" B="DESC. POR ALARMA" />
<ROW A="41500" B="PRUEBA DE COEFICIENTE" />
<ROW A="42000" B="NRO.POLIZA DEL TERCERO" />
<ROW A="42010" B="ASEGURADORA DEL TERCERO" />
<ROW A="42020" B="INDICADOR DE REQUERIDO" />
<ROW A="43000" B="INDICADOR DE INVALIDEZ" />
<ROW A="44000" B="PORCENT. INCIDENCIA DAÑO" />
<ROW A="44010" B="SOLICITUD DE S.O.S" />
<ROW A="44020" B="INTERVENCION DE BOMBEROS" />
<ROW A="44030" B="LUGAR DE ENTREGA" />
<ROW A="44040" B="DOMICILIO DE ENTREGA" />
<ROW A="45000" B="PESO" />
<ROW A="45010" B="MARCA" />
<ROW A="45015" B="MARCAS VENTA WEB" />
<ROW A="45020" B="MODELO" />
<ROW A="45022" B="AÑO-TERC" />
<ROW A="45024" B="PESO" />
<ROW A="45025" B="POTENCIA" />
<ROW A="45026" B="DIRECCION" />
<ROW A="45027" B="TRACCION" />
<ROW A="45028" B="FRENOS" />
<ROW A="45029" B="AIRBAG" />
<ROW A="45030" B="DISP. ANTIASALTO" />
<ROW A="45035" B="GRUPO-MODELO-AUTO" />
<ROW A="45050" B="FECHA INSTALACION RASTREADOR" />
<ROW A="46010" B="MARCA-INFO" />
<ROW A="46020" B="MODELOS EXCEPTUADOS" />
<ROW A="46030" B="GRUA CAMIONES" />
<ROW A="46032" B="SERVICIO DE GRUA" />
<ROW A="46033" B="AON ASSIST" />
<ROW A="46035" B="CATEG. IVA VS. TIPO DE VEH." />
<ROW A="46040" B="RASTREADOR VEHICULAR" />
<ROW A="46045" B="GAS NATURAL COMPRIMIDO" />
<ROW A="46050" B="MARCA RASTREADOR" />
<ROW A="46055" B="LUGAR DE GUARDA" />
<ROW A="46060" B="AUXILIO MECANICO" />
<ROW A="46061" B="LIVIANOS EXCEDIDOS" />
<ROW A="46065" B="RC CONOSUR" />
<ROW A="46070" B="TIPO POLIZA FACTURACION" />
<ROW A="46075" B="TIPO DE FACTURACION" />
<ROW A="46080" B="CANTIDAD DE LICENCIAS" />
<ROW A="46085" B="FOOD TRUCK" />
<ROW A="46090" B="FRANQUICIA POR DAÑO" />
<ROW A="46091" B="FRANQUICIA NUEVA" />
<ROW A="46092" B="DESCRIPCION  FRANQUICIA" />
<ROW A="46095" B="NO TERC. TRANSPORTADOS (CACO 3.1)" />
<ROW A="46100" B="KILOMETRAJE" />
<ROW A="46110" B="CANT. DE CUBIERTAS" />
<ROW A="46200" B="ALARMA DE FABRICA" />
<ROW A="46210" B="IMPURA O TRADICIONAL" />
<ROW A="46250" B="CASCO CONOSUR" />
<ROW A="46260" B="MUESTRA O NO MUESTRA" />
<ROW A="46300" B="COD. TARIFACION DE FRANQUICIA" />
<ROW A="47001" B="LICENCIA 1" />
<ROW A="47002" B="TITULAR 1" />
<ROW A="47003" B="LICENCIA 2" />
<ROW A="47004" B="TITULAR 2" />
<ROW A="47005" B="LICENCIA 3" />
<ROW A="47006" B="TITULAR 3" />
<ROW A="47007" B="LICENCIA 4" />
<ROW A="47008" B="TITULAR 4" />
<ROW A="47009" B="LICENCIA 5" />
<ROW A="47010" B="TITULAR 5" />
<ROW A="47011" B="LICENCIA 6" />
<ROW A="47012" B="TITULAR 6" />
<ROW A="47013" B="LICENCIA 7" />
<ROW A="47014" B="TITULAR 7" />
<ROW A="47015" B="LICENCIA 8" />
<ROW A="47016" B="TITULAR 8" />
<ROW A="47017" B="LICENCIA 9" />
<ROW A="47018" B="TITULAR 9" />
<ROW A="47019" B="LICENCIA 10" />
<ROW A="47020" B="TITULAR 10" />
<ROW A="47021" B="LICENCIA 11" />
<ROW A="47022" B="TITULAR 11" />
<ROW A="47023" B="LICENCIA 12" />
<ROW A="47024" B="TITULAR 12" />
<ROW A="47025" B="LICENCIA 13" />
<ROW A="47026" B="TITULAR 13" />
<ROW A="47027" B="LICENCIA 14" />
<ROW A="47028" B="TITULAR 14" />
<ROW A="47029" B="LICENCIA 15" />
<ROW A="47030" B="TITULAR 15" />
<ROW A="47031" B="LICENCIA 16" />
<ROW A="47032" B="TITULAR 16" />
<ROW A="47033" B="LICENCIA 17" />
<ROW A="47034" B="TITULAR 17" />
<ROW A="47035" B="LICENCIA 18" />
<ROW A="47036" B="TITULAR 18" />
<ROW A="47037" B="LICENCIA 19" />
<ROW A="47038" B="TITULAR 19" />
<ROW A="47039" B="LICENCIA 20" />
<ROW A="47040" B="TITULAR 20" />
<ROW A="47041" B="LICENCIA 21" />
<ROW A="47042" B="TITULAR 21" />
<ROW A="47043" B="LICENCIA 22" />
<ROW A="47044" B="TITULAR 22" />
<ROW A="47045" B="LICENCIA 23" />
<ROW A="47046" B="TITULAR 23" />
<ROW A="47047" B="LICENCIA 24" />
<ROW A="47048" B="TITULAR 24" />
<ROW A="47049" B="LICENCIA 25" />
<ROW A="47050" B="TITULAR 25" />
<ROW A="47051" B="LICENCIA 26" />
<ROW A="47052" B="TITULAR 26" />
<ROW A="47053" B="LICENCIA 27" />
<ROW A="47054" B="TITULAR 27" />
<ROW A="47055" B="LICENCIA 28" />
<ROW A="47056" B="TITULAR 28" />
<ROW A="47057" B="LICENCIA 29" />
<ROW A="47058" B="TITULAR 29" />
<ROW A="47059" B="LICENCIA 30" />
<ROW A="47060" B="TITULAR 30" />
<ROW A="47061" B="LICENCIA 31" />
<ROW A="47062" B="TITULAR 31" />
<ROW A="47063" B="LICENCIA 32" />
<ROW A="47064" B="TITULAR 32" />
<ROW A="47065" B="LICENCIA 33" />
<ROW A="47066" B="TITULAR 33" />
<ROW A="47067" B="LICENCIA 34" />
<ROW A="47068" B="TITULAR 34" />
<ROW A="47069" B="LICENCIA 35" />
<ROW A="47070" B="TITULAR 35" />
<ROW A="47071" B="LICENCIA 36" />
<ROW A="47072" B="TITULAR 36" />
<ROW A="47073" B="LICENCIA 37" />
<ROW A="47074" B="TITULAR 37" />
<ROW A="47075" B="LICENCIA 38" />
<ROW A="47076" B="TITULAR 38" />
<ROW A="47077" B="LICENCIA 39" />
<ROW A="47078" B="TITULAR 39" />
<ROW A="47079" B="LICENCIA 40" />
<ROW A="47080" B="TITULAR 40" />
<ROW A="47081" B="LICENCIA 41" />
<ROW A="47082" B="TITULAR 41" />
<ROW A="47083" B="LICENCIA 42" />
<ROW A="47084" B="TITULAR 42" />
<ROW A="47085" B="LICENCIA 43" />
<ROW A="47086" B="TITULAR 43" />
<ROW A="47087" B="LICENCIA 44" />
<ROW A="47088" B="TITULAR 44" />
<ROW A="47089" B="LICENCIA 45" />
<ROW A="47090" B="TITULAR 45" />
<ROW A="47091" B="LICENCIA 46" />
<ROW A="47092" B="TITULAR 46" />
<ROW A="47093" B="LICENCIA 47" />
<ROW A="47094" B="TITULAR 47" />
<ROW A="47095" B="LICENCIA 48" />
<ROW A="47096" B="TITULAR 48" />
<ROW A="47097" B="LICENCIA 49" />
<ROW A="47098" B="TITULAR 49" />
<ROW A="47099" B="LICENCIA 50" />
<ROW A="47100" B="TITULAR 50" />
<ROW A="47101" B="LICENCIA 51" />
<ROW A="47102" B="TITULAR 51" />
<ROW A="47103" B="LICENCIA 52" />
<ROW A="47104" B="TITULAR 52" />
<ROW A="47105" B="LICENCIA 53" />
<ROW A="47106" B="TITULAR 53" />
<ROW A="47107" B="LICENCIA 54" />
<ROW A="47108" B="TITULAR 54" />
<ROW A="47109" B="LICENCIA 55" />
<ROW A="47110" B="TITULAR 55" />
<ROW A="47111" B="LICENCIA 56" />
<ROW A="47112" B="TITULAR 56" />
<ROW A="47113" B="LICENCIA 57" />
<ROW A="47114" B="TITULAR 57" />
<ROW A="47115" B="LICENCIA 58" />
<ROW A="47116" B="TITULAR 58" />
<ROW A="47117" B="LICENCIA 59" />
<ROW A="47118" B="TITULAR 59" />
<ROW A="47119" B="LICENCIA 60" />
<ROW A="47120" B="TITULAR 60" />
<ROW A="47121" B="LICENCIA 61" />
<ROW A="47122" B="TITULAR 61" />
<ROW A="47123" B="LICENCIA 62" />
<ROW A="47124" B="TITULAR 62" />
<ROW A="47125" B="LICENCIA 63" />
<ROW A="47126" B="TITULAR 63" />
<ROW A="47127" B="LICENCIA 64" />
<ROW A="47128" B="TITULAR 64" />
<ROW A="47129" B="LICENCIA 65" />
<ROW A="47130" B="TITULAR 65" />
<ROW A="47131" B="LICENCIA 66" />
<ROW A="47132" B="TITULAR 66" />
<ROW A="47133" B="LICENCIA 67" />
<ROW A="47134" B="TITULAR 67" />
<ROW A="47135" B="LICENCIA 68" />
<ROW A="47136" B="TITULAR 68" />
<ROW A="47137" B="LICENCIA 69" />
<ROW A="47138" B="TITULAR 69" />
<ROW A="47139" B="LICENCIA 70" />
<ROW A="47140" B="TITULAR 70" />
<ROW A="47141" B="LICENCIA 71" />
<ROW A="47142" B="TITULAR 71" />
<ROW A="47143" B="LICENCIA 72" />
<ROW A="47144" B="TITULAR 72" />
<ROW A="47145" B="LICENCIA 73" />
<ROW A="47146" B="TITULAR 73" />
<ROW A="47147" B="LICENCIA 74" />
<ROW A="47148" B="TITULAR 74" />
<ROW A="47149" B="LICENCIA 75" />
<ROW A="47150" B="TITULAR 75" />
<ROW A="47151" B="LICENCIA 76" />
<ROW A="47152" B="TITULAR 76" />
<ROW A="47153" B="LICENCIA 77" />
<ROW A="47154" B="TITULAR 77" />
<ROW A="47155" B="LICENCIA 78" />
<ROW A="47156" B="TITULAR 78" />
<ROW A="47157" B="LICENCIA 79" />
<ROW A="47158" B="TITULAR 79" />
<ROW A="47159" B="LICENCIA 80" />
<ROW A="47160" B="TITULAR 80" />
<ROW A="47161" B="LICENCIA 81" />
<ROW A="47162" B="TITULAR 81" />
<ROW A="47163" B="LICENCIA 82" />
<ROW A="47164" B="TITULAR 82" />
<ROW A="47165" B="LICENCIA 83" />
<ROW A="47166" B="TITULAR 83" />
<ROW A="47167" B="LICENCIA 84" />
<ROW A="47168" B="TITULAR 84" />
<ROW A="47169" B="LICENCIA 85" />
<ROW A="47170" B="TITULAR 85" />
<ROW A="47171" B="LICENCIA 86" />
<ROW A="47172" B="TITULAR 86" />
<ROW A="47173" B="LICENCIA 87" />
<ROW A="47174" B="TITULAR 87" />
<ROW A="47175" B="LICENCIA 88" />
<ROW A="47176" B="TITULAR 88" />
<ROW A="47177" B="LICENCIA 89" />
<ROW A="47178" B="TITULAR 89" />
<ROW A="47179" B="LICENCIA 90" />
<ROW A="47180" B="TITULAR 90" />
<ROW A="47181" B="LICENCIA 91" />
<ROW A="47182" B="TITULAR 91" />
<ROW A="47183" B="LICENCIA 92" />
<ROW A="47184" B="TITULAR 92" />
<ROW A="47185" B="LICENCIA 93" />
<ROW A="47186" B="TITULAR 93" />
<ROW A="47187" B="LICENCIA 94" />
<ROW A="47188" B="TITULAR 94" />
<ROW A="47189" B="LICENCIA 95" />
<ROW A="47190" B="TITULAR 95" />
<ROW A="47191" B="LICENCIA 96" />
<ROW A="47192" B="TITULAR 96" />
<ROW A="47193" B="LICENCIA 97" />
<ROW A="47194" B="TITULAR 97" />
<ROW A="47195" B="LICENCIA 98" />
<ROW A="47196" B="TITULAR 98" />
<ROW A="47197" B="LICENCIA 99" />
<ROW A="47198" B="TITULAR 99" />
<ROW A="47199" B="LICENCIA 100" />
<ROW A="47200" B="TITULAR 100" />
<ROW A="47201" B="LICENCIA 101" />
<ROW A="47202" B="TITULAR 101" />
<ROW A="47203" B="LICENCIA 102" />
<ROW A="47204" B="TITULAR 102" />
<ROW A="47205" B="LICENCIA 103" />
<ROW A="47206" B="TITULAR 103" />
<ROW A="47207" B="LICENCIA 104" />
<ROW A="47208" B="TITULAR 104" />
<ROW A="47209" B="LICENCIA 105" />
<ROW A="47210" B="TITULAR 105" />
<ROW A="47211" B="LICENCIA 106" />
<ROW A="47212" B="TITULAR 106" />
<ROW A="47213" B="LICENCIA 107" />
<ROW A="47214" B="TITULAR 107" />
<ROW A="47215" B="LICENCIA 108" />
<ROW A="47216" B="TITULAR 108" />
<ROW A="47217" B="LICENCIA 109" />
<ROW A="47218" B="TITULAR 109" />
<ROW A="47219" B="LICENCIA 110" />
<ROW A="47220" B="TITULAR 110" />
<ROW A="47221" B="LICENCIA 111" />
<ROW A="47222" B="TITULAR 111" />
<ROW A="47223" B="LICENCIA 112" />
<ROW A="47224" B="TITULAR 112" />
<ROW A="47225" B="LICENCIA 113" />
<ROW A="47226" B="TITULAR 113" />
<ROW A="47227" B="LICENCIA 114" />
<ROW A="47228" B="TITULAR 114" />
<ROW A="47229" B="LICENCIA 115" />
<ROW A="47230" B="TITULAR 115" />
<ROW A="47231" B="LICENCIA 116" />
<ROW A="47232" B="TITULAR 116" />
<ROW A="47233" B="LICENCIA 117" />
<ROW A="47234" B="TITULAR 117" />
<ROW A="47235" B="LICENCIA 118" />
<ROW A="47236" B="TITULAR 118" />
<ROW A="47237" B="LICENCIA 119" />
<ROW A="47238" B="TITULAR 119" />
<ROW A="47239" B="LICENCIA 120" />
<ROW A="47240" B="TITULAR 120" />
<ROW A="47241" B="LICENCIA 121" />
<ROW A="47242" B="TITULAR 121" />
<ROW A="47243" B="LICENCIA 122" />
<ROW A="47244" B="TITULAR 122" />
<ROW A="47245" B="LICENCIA 123" />
<ROW A="47246" B="TITULAR 123" />
<ROW A="47247" B="LICENCIA 124" />
<ROW A="47248" B="TITULAR 124" />
<ROW A="47249" B="LICENCIA 125" />
<ROW A="47250" B="TITULAR 125" />
<ROW A="47251" B="LICENCIA 126" />
<ROW A="47252" B="TITULAR 126" />
<ROW A="47253" B="LICENCIA 127" />
<ROW A="47254" B="TITULAR 127" />
<ROW A="47255" B="LICENCIA 128" />
<ROW A="47256" B="TITULAR 128" />
<ROW A="47257" B="LICENCIA 129" />
<ROW A="47258" B="TITULAR 129" />
<ROW A="47259" B="LICENCIA 130" />
<ROW A="47260" B="TITULAR 130" />
<ROW A="47261" B="LICENCIA 131" />
<ROW A="47262" B="TITULAR 131" />
<ROW A="47263" B="LICENCIA 132" />
<ROW A="47264" B="TITULAR 132" />
<ROW A="47265" B="LICENCIA 133" />
<ROW A="47266" B="TITULAR 133" />
<ROW A="47267" B="LICENCIA 134" />
<ROW A="47268" B="TITULAR 134" />
<ROW A="47269" B="LICENCIA 135" />
<ROW A="47270" B="TITULAR 135" />
<ROW A="47271" B="LICENCIA 136" />
<ROW A="47272" B="TITULAR 136" />
<ROW A="47273" B="LICENCIA 137" />
<ROW A="47274" B="TITULAR 137" />
<ROW A="47275" B="LICENCIA 138" />
<ROW A="47276" B="TITULAR 138" />
<ROW A="47277" B="LICENCIA 139" />
<ROW A="47278" B="TITULAR 139" />
<ROW A="47279" B="LICENCIA 140" />
<ROW A="47280" B="TITULAR 140" />
<ROW A="47281" B="LICENCIA 141" />
<ROW A="47282" B="TITULAR 141" />
<ROW A="47283" B="LICENCIA 142" />
<ROW A="47284" B="TITULAR 142" />
<ROW A="47285" B="LICENCIA 143" />
<ROW A="47286" B="TITULAR 143" />
<ROW A="47287" B="LICENCIA 144" />
<ROW A="47288" B="TITULAR 144" />
<ROW A="47289" B="LICENCIA 145" />
<ROW A="47290" B="TITULAR 145" />
<ROW A="47291" B="LICENCIA 146" />
<ROW A="47292" B="TITULAR 146" />
<ROW A="47293" B="LICENCIA 147" />
<ROW A="47294" B="TITULAR 147" />
<ROW A="47295" B="LICENCIA 148" />
<ROW A="47296" B="TITULAR 148" />
<ROW A="47297" B="LICENCIA 149" />
<ROW A="47298" B="TITULAR 149" />
<ROW A="47299" B="LICENCIA 150" />
<ROW A="47300" B="TITULAR 150" />
<ROW A="47301" B="LICENCIA 151" />
<ROW A="47302" B="TITULAR 151" />
<ROW A="47303" B="LICENCIA 152" />
<ROW A="47304" B="TITULAR 152" />
<ROW A="47305" B="LICENCIA 153" />
<ROW A="47306" B="TITULAR 153" />
<ROW A="47307" B="LICENCIA 154" />
<ROW A="47308" B="TITULAR 154" />
<ROW A="47309" B="LICENCIA 155" />
<ROW A="47310" B="TITULAR 155" />
<ROW A="47311" B="LICENCIA 156" />
<ROW A="47312" B="TITULAR 156" />
<ROW A="47313" B="LICENCIA 157" />
<ROW A="47314" B="TITULAR 157" />
<ROW A="47315" B="LICENCIA 158" />
<ROW A="47316" B="TITULAR 158" />
<ROW A="47317" B="LICENCIA 159" />
<ROW A="47318" B="TITULAR 159" />
<ROW A="47319" B="LICENCIA 160" />
<ROW A="47320" B="TITULAR 160" />
<ROW A="47321" B="LICENCIA 161" />
<ROW A="47322" B="TITULAR 161" />
<ROW A="47323" B="LICENCIA 162" />
<ROW A="47324" B="TITULAR 162" />
<ROW A="47325" B="LICENCIA 163" />
<ROW A="47326" B="TITULAR 163" />
<ROW A="47327" B="LICENCIA 164" />
<ROW A="47328" B="TITULAR 164" />
<ROW A="47329" B="LICENCIA 165" />
<ROW A="47330" B="TITULAR 165" />
<ROW A="47331" B="LICENCIA 166" />
<ROW A="47332" B="TITULAR 166" />
<ROW A="47333" B="LICENCIA 167" />
<ROW A="47334" B="TITULAR 167" />
<ROW A="47335" B="LICENCIA 168" />
<ROW A="47336" B="TITULAR 168" />
<ROW A="47337" B="LICENCIA 169" />
<ROW A="47338" B="TITULAR 169" />
<ROW A="47339" B="LICENCIA 170" />
<ROW A="47340" B="TITULAR 170" />
<ROW A="47341" B="LICENCIA 171" />
<ROW A="47342" B="TITULAR 171" />
<ROW A="47343" B="LICENCIA 172" />
<ROW A="47344" B="TITULAR 172" />
<ROW A="47345" B="LICENCIA 173" />
<ROW A="47346" B="TITULAR 173" />
<ROW A="47347" B="LICENCIA 174" />
<ROW A="47348" B="TITULAR 174" />
<ROW A="47349" B="LICENCIA 175" />
<ROW A="47350" B="TITULAR 175" />
<ROW A="47351" B="LICENCIA 176" />
<ROW A="47352" B="TITULAR 176" />
<ROW A="47353" B="LICENCIA 177" />
<ROW A="47354" B="TITULAR 177" />
<ROW A="47355" B="LICENCIA 178" />
<ROW A="47356" B="TITULAR 178" />
<ROW A="47357" B="LICENCIA 179" />
<ROW A="47358" B="TITULAR 179" />
<ROW A="47359" B="LICENCIA 180" />
<ROW A="47360" B="TITULAR 180" />
<ROW A="47361" B="LICENCIA 181" />
<ROW A="47362" B="TITULAR 181" />
<ROW A="47363" B="LICENCIA 182" />
<ROW A="47364" B="TITULAR 182" />
<ROW A="47365" B="LICENCIA 183" />
<ROW A="47366" B="TITULAR 183" />
<ROW A="47367" B="LICENCIA 184" />
<ROW A="47368" B="TITULAR 184" />
<ROW A="47369" B="LICENCIA 185" />
<ROW A="47370" B="TITULAR 185" />
<ROW A="47371" B="LICENCIA 186" />
<ROW A="47372" B="TITULAR 186" />
<ROW A="47373" B="LICENCIA 187" />
<ROW A="47374" B="TITULAR 187" />
<ROW A="47375" B="LICENCIA 188" />
<ROW A="47376" B="TITULAR 188" />
<ROW A="47377" B="LICENCIA 189" />
<ROW A="47378" B="TITULAR 189" />
<ROW A="47379" B="LICENCIA 190" />
<ROW A="47380" B="TITULAR 190" />
<ROW A="47381" B="LICENCIA 191" />
<ROW A="47382" B="TITULAR 191" />
<ROW A="47383" B="LICENCIA 192" />
<ROW A="47384" B="TITULAR 192" />
<ROW A="47385" B="LICENCIA 193" />
<ROW A="47386" B="TITULAR 193" />
<ROW A="47387" B="LICENCIA 194" />
<ROW A="47388" B="TITULAR 194" />
<ROW A="47389" B="LICENCIA 195" />
<ROW A="47390" B="TITULAR 195" />
<ROW A="47391" B="LICENCIA 196" />
<ROW A="47392" B="TITULAR 196" />
<ROW A="47393" B="LICENCIA 197" />
<ROW A="47394" B="TITULAR 197" />
<ROW A="47395" B="LICENCIA 198" />
<ROW A="47396" B="TITULAR 198" />
<ROW A="47397" B="LICENCIA 199" />
<ROW A="47398" B="TITULAR 199" />
<ROW A="47399" B="LICENCIA 200" />
<ROW A="47400" B="TITULAR 200" />
<ROW A="47500" B="SEGURO DE TRANSITO" />
<ROW A="48000" B="CARACTERISTICA DE OCURRENCIA" />
<ROW A="48010" B="RANGOS DE INCAPACIDAD" />
<ROW A="48020" B="TALLER DEL TERCERO" />
<ROW A="48030" B="VEHICULO NO COTIZABLE" />
<ROW A="48040" B="MARCA DE CUBIERTAS" />
<ROW A="48045" B="MARCA DE CUB.AUXILIO" />
<ROW A="48050" B="MEDIDA DE CUBIERTAS" />
<ROW A="48055" B="MEDIDA DE CUB.AUXILIO" />
<ROW A="48060" B="DESGASTE DE CUBIERTAS" />
<ROW A="48065" B="DESGASTE DE CUB.AUXILIO" />
<ROW A="48070" B="ESTADO DE CUBIERTAS" />
<ROW A="48075" B="ESTADO DE CUB.AUXILIO" />
<ROW A="48080" B="ESTADO DEL VEHICULO" />
<ROW A="48090" B="KILOMETRAJE" />
<ROW A="48100" B="COLOR" />
<ROW A="48110" B="PARABRISAS" />
<ROW A="48120" B="CERRADURA" />
<ROW A="48130" B="LUNETA" />
<ROW A="48140" B="ANTENA" />
<ROW A="48150" B="ALARMA FUNCIONA" />
<ROW A="48155" B="MARCA ALARMA" />
<ROW A="48160" B="ALARMA SONORA" />
<ROW A="48170" B="ALARMA LUMINICA" />
<ROW A="48180" B="ALARMA CONTROL REMOTO" />
<ROW A="48185" B="ALARMA LLAVE" />
<ROW A="48190" B="SENSORES VOLUMETRICOS" />
<ROW A="48200" B="SENSORES APERTURA PUERTAS" />
<ROW A="48210" B="SENSORES APERTURA CAPOT" />
<ROW A="48220" B="SENSORES APERTURA BAUL" />
<ROW A="48225" B="INDICADOR PROD. PROMOCIONADO" />
<ROW A="48230" B="NRO. DE OBLEA GNC" />
<ROW A="48240" B="VENC. DE OBLEA" />
<ROW A="48250" B="NRO. DE REGULADOR GNC" />
<ROW A="48260" B="MARCA REGULADOR" />
<ROW A="48265" B="DNI TIT. EQUIPO DE GAS" />
<ROW A="48270" B="NRO. CILINDRO 1 GNC" />
<ROW A="48280" B="MARCA CILINDRO 1 GNC" />
<ROW A="48285" B="VENC. CILINDRO 1 GNC" />
<ROW A="48286" B="VENC. CILINDRO 2 GNC" />
<ROW A="48287" B="VENC. CILINDRO 3 GNC" />
<ROW A="48288" B="VENC. VTV" />
<ROW A="48290" B="NRO. CILINDRO 2 GNC" />
<ROW A="48300" B="MARCA CILINDRO 2 GNC" />
<ROW A="48310" B="NRO. CILINDRO 3 GNC" />
<ROW A="48320" B="MARCA CILINDRO 3 GNC" />
<ROW A="48330" B="DOC. CEDULA AMARILLA" />
<ROW A="48340" B="EXAMEN DE ALCOHOLEMIA" />
<ROW A="48350" B="DESC. DE HORARIO" />
<ROW A="48360" B="ESTADO DEL TIEMPO" />
<ROW A="48370" B="NRO. DE RUTA" />
<ROW A="48380" B="RUTA KM." />
<ROW A="48390" B="TIPO DE RUTA" />
<ROW A="48400" B="CRUCE CON RUTA NRO." />
<ROW A="48410" B="SEÑAL CRUCE DE RUTA" />
<ROW A="48420" B="CRUCE DE TREN" />
<ROW A="48430" B="EXISTE BARRERA" />
<ROW A="48440" B="SEÑAL CRUCE DE TREN" />
<ROW A="48450" B="ESTADO DE LA BARRERA" />
<ROW A="48460" B="EXISTE SEMAFORO" />
<ROW A="48470" B="FUNCIONAMIENTO DEL SEMAFORO" />
<ROW A="48480" B="COLOR DEL SEMAFORO" />
<ROW A="48490" B="TIPO DE CALZADA" />
<ROW A="48500" B="ESTADO DE CALZADA" />
<ROW A="48510" B="PROPIETARIO O CONDUCTOR" />
<ROW A="48520" B="TIPO DE COLISION" />
<ROW A="48530" B="CONSECUENCIA DE COLISION" />
<ROW A="48540" B="UBICACION DEL ACCIDENTE" />
<ROW A="48550" B="COLISION CON" />
<ROW A="48600" B="TIPO DE LLANTA" />
<ROW A="49030" B="ZONA ADICIONAL INTERASEGURADOS" />
<ROW A="49040" B="COB.ADICIONAL INTERASEGURADOS" />
<ROW A="49050" B="PAISES LIMITROFES" />
<ROW A="49060" B="REMEDIACION" />
<ROW A="49070" B="CAMPOS PETROL. Y/O AEROPUERTOS" />
<ROW A="49080" B="ALTA GAMA" />
<ROW A="49090" B="RESIDUOS ESPECIALES" />
<ROW A="49100" B="DEFINICION DE ENVIO LO-JACK" />
<ROW A="49200" B="CATEGORIA DE ZONA" />
<ROW A="49250" B="RC-CON O SIN SUB-LIMITE" />
<ROW A="49300" B="COEF. ADM A PRIMA AUTOS" />
<ROW A="49400" B="TELEFONO DEL CONDUCTOR" />
<ROW A="49450" B="TIPO DOC. DEL CONDUCTOR" />
<ROW A="49500" B="NRO. DOC. DEL CONDUCTOR" />
<ROW A="49550" B="DENUNCIA POLICIAL" />
<ROW A="49600" B="AMBULANCIA" />
<ROW A="49650" B="PRESENTO REGISTRO?" />
<ROW A="49660" B="ESTADO DEL REGISTRO" />
<ROW A="49670" B="TRAMITE DE BAJA" />
<ROW A="49680" B="TIPO DE BAJA" />
<ROW A="49690" B="MOTIVO DE DAÑO TOTAL" />
<ROW A="49700" B="CADI 19.1 (TALLER)" />
<ROW A="49710" B="RIESGO CUBIERTO" />
<ROW A="49720" B="REPARADO" />
<ROW A="49730" B="TIPO DE INTERVENCION" />
<ROW A="50100" B="TIPO DE CRISTAL" />
<ROW A="50200" B="METROS CUADRADOS" />
<ROW A="50300" B="FORMA DE COLOCACION" />
<ROW A="50350" B="FONDO PINTADO AL EXTERIOR" />
<ROW A="50400" B="GRANIZO" />
<ROW A="50500" B="TERREMOTO" />
<ROW A="50600" B="HURACAN,CICLON, TORNADO" />
<ROW A="50700" B="INCENDIO,RAYO Y/O EXPLOSION" />
<ROW A="50800" B="DESC. CANTIDAD DE PIEZAS" />
<ROW A="50900" B="DESC. ELEVACION O BAJO NIVEL" />
<ROW A="51000" B="TIPO DE CRISTALES ASEGURA2" />
<ROW A="51010" B="CANTIDAD DE MODULOS" />
<ROW A="60001" B="USO DE VIVIENDA" />
<ROW A="60002" B="TIPO DE CONSTRUCCION" />
<ROW A="60003" B="TV/AUDIO" />
<ROW A="60004" B="COMPUTADOR" />
<ROW A="60005" B="OTROS" />
<ROW A="60006" B="SUELDOS: NUMERO DE VIAJES" />
<ROW A="60007" B="FUNCION COMERCIAL" />
<ROW A="60009" B="OBJETOS DIVERSOS" />
<ROW A="60010" B="VIGILANCIA ARMADA" />
<ROW A="60011" B="ABERTURA" />
<ROW A="60012" B="LINDERO BALDIO U OBRA EN CONSTRUCCION" />
<ROW A="60013" B="CERRADURA TRABEX" />
<ROW A="60014" B="TIPO DE MEDIANERA O CERCO" />
<ROW A="60015" B="TIPO DE VIVIENDA" />
<ROW A="60016" B="AMBITO DE LA COBERTURA" />
<ROW A="60017" B="AMPLIACIÓN COB. EN VEHÍCULOS" />
<ROW A="60018" B="ESTADIA PARA SUELDOS" />
<ROW A="60019" B="NOMBRE DEL RESPONSABLE" />
<ROW A="60020" B="DOCUMENTO DE IDENTIDAD" />
<ROW A="60021" B="CANTIDAD DE UBICACIONES" />
<ROW A="60022" B="TIPO DE VIVIENDAS" />
<ROW A="60030" B="ROBO APLICA A:" />
<ROW A="60031" B="SUMA P.R.A. INDISTINTA PARA:" />
<ROW A="60032" B="REPOS. A NUEVO ELECTRODOMEST" />
<ROW A="60033" B="CABINA BLINDADA (C. C9-C10)" />
<ROW A="60034" B="TESORO BLINDADO (C. C11-C12)" />
<ROW A="60035" B="CAJAS/VENTANILLAS EN PISOS ALTOS" />
<ROW A="60036" B="BUZON SIN LLAVE (C. C13)" />
<ROW A="60037" B="PRESENCIA DE PUBLICO (C.C3)" />
<ROW A="60038" B="FRANQUICIA" />
<ROW A="60039" B="VALORES EN MONEDA EXTRANJERA" />
<ROW A="60040" B="OTROS VALORES" />
<ROW A="60041" B="ZONA ORIGEN DE LOS TRANSITOS" />
<ROW A="60042" B="FRECUENCIA DE LOS VIAJES" />
<ROW A="60043" B="DISTANCIAS" />
<ROW A="60044" B="COBRADORES: SUMA INDISTINTA PARA" />
<ROW A="60045" B="SEGURIDAD EN TRANSITOS" />
<ROW A="60046" B="VEHICULO CON BUZON-CAJA FUERTE" />
<ROW A="60047" B="VEHICULO BLINDADO" />
<ROW A="60048" B="ZONA DOMICILIO DE GUARDA" />
<ROW A="60049" B="CUADROS: COBERTURAS ESPECIALES" />
<ROW A="60050" B="DAÑOS POR TENSION" />
<ROW A="60051" B="CARGO QUE OCUPA" />
<ROW A="60052" B="SUMA INDISTINTA PARA" />
<ROW A="60053" B="POLIZA DE OTROS RAMOS VIGENTE" />
<ROW A="60054" B="VENTANILLAS: SUMA INDISTINTA" />
<ROW A="60055" B="FIDELIDAD EMPLEADOS SUMA INDISTINTA" />
<ROW A="60056" B="COBRADORES: SUMA INDISTINTA PARA" />
<ROW A="60057" B="DINERO EN PODER PLAYEROS-SUM INDISTINTA" />
<ROW A="60058" B="CAJAS REGISTRADORAS: SUMA INDISTINTA" />
<ROW A="60060" B="TIPO DE BICICLETA" />
<ROW A="60061" B="AÑO DE FABRICACION" />
<ROW A="60063" B="COMPETENCIA AMATEUR" />
<ROW A="60064" B="PLAN DE COBERTURA" />
<ROW A="60065" B="MARCA / MODELO" />
<ROW A="60067" B="MATERIAL DEL CUADRO" />
<ROW A="60068" B="COLOR" />
<ROW A="60069" B="RODADO" />
<ROW A="60070" B="NUMERO DE CUADRO" />
<ROW A="60071" B="TAMAÑO DEL CUADRO" />
<ROW A="60072" B="MARCA / MODELO DE RUEDAS" />
<ROW A="60073" B="MARCA / MODELO GRUPO TRANSMISION" />
<ROW A="60075" B="FRANQUICIA DEDUCIBLE" />
<ROW A="60076" B="LOCALIDAD DE GUARDA" />
<ROW A="60077" B="NUMERO DE ITEMS" />
<ROW A="70000" B="CATEGORIAS" />
<ROW A="70010" B="DESCRIP. DEL RIESGO" />
<ROW A="70020" B="CONCESIONARIO / TALLER" />
<ROW A="70030" B="TIPO DE VENTA" />
<ROW A="70040" B="NRO. DE MOTOR" />
<ROW A="70050" B="NRO. DE CHASIS" />
<ROW A="70060" B="PATENTE" />
<ROW A="70070" B="KMS. RECORRIDOS" />
<ROW A="70080" B="FECHA DE INSC. EN REGISTRO" />
<ROW A="70090" B="AÑO DE FABRICACION" />
<ROW A="70100" B="MARCA DE PALOS" />
<ROW A="70101" B="YARDAS" />
<ROW A="70102" B="CATEGORIA DE JUGADOR" />
<ROW A="70103" B="CANTIDAD DE JUGADORES" />
<ROW A="70104" B="RONDAS" />
<ROW A="70200" B="PARAM. DE COBERTURA" />
<ROW A="70210" B="MARCAS" />
<ROW A="70220" B="LIM. DE RESARCIMIENTO" />
<ROW A="70230" B="F. INICIO DE COBERTURA" />
<ROW A="70310" B="TIPO DE SEGURO" />
<ROW A="70320" B="USUARIO TJ PREMIUM" />
<ROW A="70330" B="DESCUENTO CANTIDAD" />
<ROW A="70340" B="EDAD PROMEDIO" />
<ROW A="70350" B="DIS. GEOGRAFICA" />
<ROW A="70400" B="PERSONAS CUBIERTAS :" />
<ROW A="70401" B="NOMBRE ASEGURADO 1" />
<ROW A="70402" B="CUIL ASEGURADO 1" />
<ROW A="70403" B="NOMBRE ASEGURADO 2" />
<ROW A="70404" B="CUIL ASEGURADO 2" />
<ROW A="70405" B="NOMBRE ASEGURADO 3" />
<ROW A="70406" B="CUIL ASEGURADO 3" />
<ROW A="70407" B="NOMBRE ASEGURADO 4" />
<ROW A="70408" B="CUIL ASEGURADO 4" />
<ROW A="70500" B="AÑO DE NACIMIENTO" />
<ROW A="70510" B="RAZA" />
<ROW A="70520" B="PLAN DE VACUNACION" />
<ROW A="70530" B="CERTIFICADO CINOLOGICO" />
<ROW A="70540" B="AMPLIACION CRIA DE LA MASCOTA" />
<ROW A="70550" B="AMBITO DE COBERTURA" />
<ROW A="70560" B="SE EMPLEA PARA EXPOSICION, ETC?" />
<ROW A="70570" B="SEXO" />
<ROW A="70580" B="NOMBRE" />
<ROW A="80001" B="CANTIDAD DE PLANTAS A DEMOLER" />
<ROW A="80002" B="ANTIGUEDAD INMUEBLES LINDEROS" />
<ROW A="80003" B="SUPERFICIE CUBIERTA A DEMOLER" />
<ROW A="80004" B="EXISTENCIA DE LINDEROS (DEMOLICIONES)" />
<ROW A="80005" B="CANTIDAD DE PLANTAS EDIFICIOS LINDEROS" />
<ROW A="80006" B="DESTINO/ USO EDIFICIO (CALDERAS)" />
<ROW A="80007" B="CANTIDAD DE CALDERAS" />
<ROW A="80008" B="DESCUENTO LINDEROS (CALDERAS)" />
<ROW A="80009" B="DESTINO/ USO ASCENSORES, MONTACARGAS" />
<ROW A="80010" B="PERSONAL DESTACADO (ASCENSORISTA)" />
<ROW A="80011" B="CANTIDAD DE ASCENSORES, MONTACARGAS" />
<ROW A="80012" B="EXISTENCIA DE LINDEROS (CONSTRUCCIONES)" />
<ROW A="80014" B="RECARGOS (CONSTRUCCIONES)" />
<ROW A="80015" B="CANTIDAD PLANTAS A CONSTRUIR" />
<ROW A="80016" B="ANTIGÜEDAD INMUEBLES LINDEROS (CONSTRUCCIONES)" />
<ROW A="80017" B="CANTIDAD PLANTAS LINDEROS (CONSTRUCCIONES)" />
<ROW A="80019" B="COB.ADIC. DERRUMBE DE LINDEROS (REFACCIONES)" />
<ROW A="80020" B="COB.ADIC. FILTRACIONES A LINDEROS (REFACCIONES)" />
<ROW A="80021" B="LUGAR / PLANTA A REFACCIONAR" />
<ROW A="80022" B="LA OBRA POSEE CERRAMIENTOS?" />
<ROW A="80030" B="TIPO DE CARTEL, LETRERO" />
<ROW A="80031" B="CANTIDAD DE CARTELES, LETREROS" />
<ROW A="80032" B="CANTIDAD DE UBICACIONES" />
<ROW A="80033" B="DESTINO/ USO EDIFICIO (CALDERAS) SELF" />
<ROW A="80040" B="TIPO DE RIESGO (INC,RAYO,EXPL,DESC.EL,ESC.GAS)" />
<ROW A="80041" B="CONSTRUCCION INFERIOR" />
<ROW A="80042" B="CANTIDAD DE AUTOS" />
<ROW A="80043" B="GUARDA DE MOTOCICLETAS/BICICLETAS" />
<ROW A="80044" B="TIPO DE RIESGO (INC,RAYO,EXPL,DESC.EL,ESC.GAS) NUEVA" />
<ROW A="80050" B="TIPO DE VIVIENDA - HECHOS PRIVADOS" />
<ROW A="80051" B="USO DE MEDIOS DE TRANSPORTE" />
<ROW A="80052" B="INCLUYE CONYUGE/CONVIVIENTE" />
<ROW A="80053" B="INCLUYE HIJOS MENORES" />
<ROW A="80055" B="TIPO DE OBRA" />
<ROW A="80060" B="ZONA DONDE SE REALIZA LA OBRA" />
<ROW A="80070" B="ENCARGADO DE REGISTRO" />
<ROW A="80075" B="RC HECHOS PRIV  ASEGURA2" />
<ROW A="80080" B="COB.ESCAPE ANIMALES-CANT.HECTAREAS" />
<ROW A="80090" B="COB.ESCAPE ANIMALES-UBIC.PREDIO" />
<ROW A="80100" B="TIPO DE MAQUINA" />
<ROW A="80110" B="TIPOS DE CIUDAD" />
<ROW A="80120" B="SISTEMAS DE PROTECCION DE INCENDIO" />
<ROW A="80130" B="ACTIVIDAD DE LA COCHERA" />
<ROW A="80140" B="BUEN RESULTADO ROBO/HURTO" />
<ROW A="80150" B="CANTIDAD DE PISOS" />
<ROW A="80160" B="CANTIDAD DE ELEVADORES" />
<ROW A="80170" B="CANTIDAD DE ASCENSORES ATENDIDOS" />
<ROW A="80180" B="CANTIDAD DE TECNICOS (ASCENSORES)" />
<ROW A="80190" B="REBAJA POR CANTIDAD DE TECNICOS" />
<ROW A="80191" B="COB. SUMINISTRO ALIMENTOS" />
<ROW A="80192" B="COB.CARGA/ DESCARGA-CANT.VEHICULOS" />
<ROW A="80193" B="COB.ROTURA DE CAÑERIAS-ACTIVIDAD" />
<ROW A="80194" B="CANTIDAD DE EMPLEADOS" />
<ROW A="80195" B="CANTIDAD DE UBICACIONES DEL RIESGO" />
<ROW A="80196" B="CANT.LOCALES SUMIN.ALIMENTOS" />
<ROW A="80197" B="RC- ANIMALES USO" />
<ROW A="80198" B="COB.ROTURA DE CAÑERIAS-ACTIVIDAD" />
<ROW A="80210" B="DESCUENTO POR CANTIDAD DE MAQUINARIAS" />
<ROW A="80250" B="CANTIDAD DE UBICACIONES MAQUINARIAS" />
<ROW A="80260" B="CANTIDAD DE MAQUINARIAS / EQUIPOS" />
<ROW A="80310" B="NIVEL DE ENSEÑANZA" />
<ROW A="80400" B="CANTIDAD DE ALUMNOS" />
<ROW A="80410" B="TASA POR MIL" />
<ROW A="80411" B="FRANQUICIA GANADO" />
<ROW A="80415" B="TASA ADICIONAL" />
<ROW A="80420" B="COEF. DE VARIACION" />
<ROW A="80430" B="COEF.VARIACION REDUCIDO" />
<ROW A="80500" B="TIPO DE TINTORERIA" />
<ROW A="80510" B="CANT LOCALES DE TINTORERIA" />
<ROW A="80600" B="SUMA ASEGURADA" />
<ROW A="80610" B="FACTURACION OBRA DECLARADA" />
<ROW A="80700" B="CANT.ASCESORES POR CADA TECNICO" />
<ROW A="80800" B="LONGITUD TOTAL DE LA OBRA" />
<ROW A="80900" B="ANCHO TOTAL DE LA OBRA" />
<ROW A="80950" B="PROFUNDIDAD TOTAL DE LA OBRA" />
<ROW A="80955" B="OBRA CON CERRAMIENTOS" />
<ROW A="80960" B="CORTE DE TRANSITO VEHICULAR" />
<ROW A="80965" B="SE UTILIZA MAQUINARIA VIAL" />
<ROW A="80966" B="CUBRE DERRUMBE DE LINDEROS" />
<ROW A="80967" B="CUBRE FILTRACIONES A LINDEROS" />
<ROW A="80970" B="ACT. NO PERMITIDA PARA EMISION" />
<ROW A="80980" B="ACTIVIDAD R.C. COMPRENSIVA" />
<ROW A="80985" B="VALOR PERMITIDA EN SELF" />
<ROW A="80990" B="TASA ACT.TURISMO ALTERNATIVO/AVENTURA" />
<ROW A="80995" B="VALOR NO PERMITIDA EN SELF" />
<ROW A="81000" B="ACTIVIDAD" />
<ROW A="81001" B="TIPO DE ACTIVIDAD" />
<ROW A="81002" B="ACTIVIDADES CON SERVICIO" />
<ROW A="81003" B="CODIGOS POSTALES CON SERVICIO" />
<ROW A="81004" B="ACTIVIDAD T.R.O." />
<ROW A="81005" B="AJUSTE AUTOMATICO SUMA ASEG." />
<ROW A="81006" B="AJUSTE AUTOMATICO" />
<ROW A="81007" B="CLAUSULA ESTABILIZ. SUMA ASEGURADA" />
<ROW A="81008" B="RC AMPLIADA" />
<ROW A="81010" B="UBICACION" />
<ROW A="81020" B="TIPO DE CONSTRUCCION" />
<ROW A="81030" B="TIPO DE TECHO" />
<ROW A="81040" B="TIPO DE PAREDES" />
<ROW A="81050" B="TIPO DE FACHADA" />
<ROW A="81060" B="MATERIAL USADO" />
<ROW A="81070" B="POSEE POLIZA VIGENTE DE RS. VS." />
<ROW A="81100" B="ACTIVIDAD PERMITIDA" />
<ROW A="81200" B="CANTIDAD DE EMPLEADOS" />
<ROW A="81201" B="POTENCIA INSTALADA (HP)" />
<ROW A="81202" B="RELACION SUP.CUB./TOTAL (MT2)" />
<ROW A="81203" B="LOCALIZACION" />
<ROW A="81210" B="FACTURACIÓN ANUAL" />
<ROW A="81211" B="RELACION VTAS. ANUALES/ACTIVOS" />
<ROW A="81212" B="CANTIDAD DE PROPIETARIOS" />
<ROW A="81213" B="TIPO DE COBERTURA" />
<ROW A="81214" B="CUBRE RECL.POR PRACT.LABORALES" />
<ROW A="81215" B="PERIODO EXTENDIDO DE DENUNCIAS" />
<ROW A="81600" B="GRANIZO" />
<ROW A="81610" B="HURACAN" />
<ROW A="81620" B="TERREMOTO-INCENDIO" />
<ROW A="81630" B="TERREMOTO-DA?OS" />
<ROW A="81800" B="DISYUNTOR" />
<ROW A="82000" B="CANTIDAD ESPECTADORES POR EVENTO/ESPECTACULO" />
<ROW A="82001" B="CANTIDAD ESPECTADORES POR EVENTO/ESPECTACULO" />
<ROW A="82005" B="CANTIDAD DE EVENTOS/ESPECTACULOS" />
<ROW A="82010" B="COB. PROV. ENERGÍA ELECT. - CANT. DE HABITANTES" />
<ROW A="82020" B="ACTIVIDAD R.C. COMPRENSIVA" />
<ROW A="82030" B="ACTIVIDAD R.C. COMPRENSIVA" />
<ROW A="82040" B="ACTIVIDAD R.C. COMPRENSIVA" />
<ROW A="82050" B="COB. PRODUCTOS - FACT. ANUAL ESTIMADA" />
<ROW A="82060" B="ACTIVIDAD R.C. COMPRENSIVA" />
<ROW A="82070" B="CONSTRUCCION INFERIOR DERIVADA" />
<ROW A="82080" B="LUGAR/CARACTERISTICAS DEL RIESGO" />
<ROW A="82090" B="ACTIVIDAD R.C. COMPRENSIVA" />
<ROW A="82095" B="ACTIVIDAD R.C. COMPRENSIVA" />
<ROW A="83000" B="CUBRE ASCENSIONES" />
<ROW A="83010" B="CUBRE BUCEO" />
<ROW A="83020" B="CUBRE CABALGATA" />
<ROW A="83030" B="CUBRE CANOTAJE" />
<ROW A="83040" B="CUBRE ESCALADA" />
<ROW A="83050" B="CUBRE ESQUÍ" />
<ROW A="83060" B="CUBRE KAYAC" />
<ROW A="83070" B="CUBRE LESIONES AL CAZADOR (COTOS DE CAZA)" />
<ROW A="83080" B="CUBRE MOUNTAIN BIKE" />
<ROW A="83090" B="CUBRE PESCA" />
<ROW A="83100" B="CUBRE RAFTING" />
<ROW A="83110" B="CUBRE RAPPEL" />
<ROW A="83120" B="CUBRE TIROLESA" />
<ROW A="83130" B="CUBRE TREKKING" />
<ROW A="83140" B="CUBRE BANANA ACUÁTICA" />
<ROW A="83145" B="CUBRE CUATRICICLOS" />
<ROW A="83150" B="CUBRE PAINT BALL" />
<ROW A="83155" B="CUBRE ARQUERÍA" />
<ROW A="85000" B="CATEGORIA (PROF.SALUD)" />
<ROW A="85010" B="JEFE EQUIPO/SERVICIO" />
<ROW A="85100" B="CATEGORIAS PROF. SALUD" />
<ROW A="85110" B="CANTIDAD DE PLANTAS DEL EDIFICIO" />
<ROW A="85200" B="SUMA ASEGURADA" />
<ROW A="85300" B="TIPO DE FRANQUICIA" />
<ROW A="85310" B="FRANQUICIA" />
<ROW A="85320" B="RANGO DE SUMAS" />
<ROW A="85330" B="SUMA A CUBRIR" />
<ROW A="85340" B="EN EXCESO DE" />
<ROW A="85350" B="MEDICO INTERVINIENTE" />
<ROW A="85360" B="NOMBRE DEL PACIENTE" />
<ROW A="85370" B="CATEGORIA DE ESTABLECIMIENTO" />
<ROW A="85380" B="RESP. CIVIL CRUZADA" />
<ROW A="85385" B="RC CONTAMINACION SUBITA Y ACCIDENTAL" />
<ROW A="85390" B="NRO. MATRICULA" />
<ROW A="85400" B="TIPO DE MATRICULA" />
<ROW A="85410" B="RC COMPRENSIVA" />
<ROW A="85420" B="ZONA DE RIESGO" />
<ROW A="85430" B="RC COMPRENSIVA" />
<ROW A="85431" B="CUBRE PASANTIAS" />
<ROW A="85440" B="REQUIERE  NUEVA INSPECCION" />
<ROW A="85450" B="PROFESION" />
<ROW A="85460" B="MONTO PROMEDIO OBRAS / PROYECTOS" />
<ROW A="85470" B="DIRECTOR DE OBRA / MANTENIMIENTO" />
<ROW A="85480" B="PERIODO EXTENDIDO DE DENUNCIAS" />
<ROW A="85481" B="PERIODO EXTENDIDO DE DENUNCIAS" />
<ROW A="85482" B="PERIODO EXTENDIDO DE DENUNCIAS" />
<ROW A="85483" B="PERIODO DE NOTIFICACION AMPLIADO" />
<ROW A="85485" B="PERIODO EXTENDIDO DE DENUNCIAS" />
<ROW A="85490" B="AÑO DE COBERTURA" />
<ROW A="85500" B="FECHA INICIO PERIODO RETROACTIV." />
<ROW A="85510" B="MEDIOS DE ELEV.,PISTAS,,PARQUES DIV,PILETAS,JUEGOS" />
<ROW A="85520" B="POSEE POLIZA VIGENTE DE RS. VS." />
<ROW A="85530" B="COB. ADICIONALES ARQ./ING." />
<ROW A="85540" B="PROF. VINCULADAS A MALA PRAXIS" />
<ROW A="85550" B="PROFESION" />
<ROW A="85551" B="JURISDICCION EN LA QUE EJERCE" />
<ROW A="85552" B="CASOS ATENDIDOS" />
<ROW A="85553" B="ANTIGÜEDAD EN MATRICULA" />
<ROW A="85554" B="MATERIA A LA QUE SE DEDICA" />
<ROW A="85560" B="PROFESION  DESARROLLADA" />
<ROW A="85570" B="COB. BIENES BAJO CONTROL Y CUSTODIA" />
<ROW A="85572" B="COB. BIENES BAJO CONTROL Y CUSTODIA" />
<ROW A="85580" B="COB. CONTAMINACION SUBITA Y ACCIDENTAL" />
<ROW A="85585" B="COB CONT. SUBITA Y ACCIDENTAL - ACT. COMERCIALES" />
<ROW A="85590" B="TASA RC PRODUCTOS" />
<ROW A="85600" B="PROFESION (SALUD)" />
<ROW A="85700" B="TIPO DE PRODUCTOR" />
<ROW A="85710" B="CANTIDAD CERTIFICADOS VIGENTES (TODAS LAS CÍAS.)" />
<ROW A="85715" B="BUEN RESULTADO PROD.DE FED.PATRONAL" />
<ROW A="85720" B="PRODUCCION ANUAL EN PRIMAS" />
<ROW A="85730" B="TIPO DE MATRICULACION" />
<ROW A="85740" B="PRODUCTOR DE FED.PATRONAL" />
<ROW A="85750" B="PERIODO EXTEND.NOTIF.RECLAMOS PROD.SEG." />
<ROW A="85755" B="SOCIO DE AAPAS" />
<ROW A="85760" B="NRO. MATRICULA SSN" />
<ROW A="85770" B="CODIGO PROD. FED.PATRONAL" />
<ROW A="85780" B="ACTIVIDAD RC PRODUCTOS" />
<ROW A="85785" B="TIPO DE ACTIVIDAD RC PRODUCTOS" />
<ROW A="85790" B="TIPO DE PRODUCTO" />
<ROW A="85800" B="FACTURACION ANUAL" />
<ROW A="85810" B="TIPO DE EMBARCACION" />
<ROW A="85820" B="USO DE LA EMBARCACION" />
<ROW A="85830" B="ADICIONAL DEPORTES ACUATICOS" />
<ROW A="85840" B="ADICIONAL TRANSITO SOBRE TRAILER" />
<ROW A="85850" B="ADICIONAL DERRAMES" />
<ROW A="85855" B="ADICIONAL BIENES BAJO CONTROL Y CUSTODIA" />
<ROW A="85860" B="NRO. DE REY" />
<ROW A="85870" B="LUGAR DE GUARDA / AMARRE" />
<ROW A="85880" B="ZONA DE NAVEGACION" />
<ROW A="85900" B="VARIACION FRANQUICIA" />
<ROW A="85910" B="VARIACION FRANQUICIA (RC AMBIENTAL)" />
<ROW A="85915" B="VARIACION FRANQUICIA (RC.PROD.)" />
<ROW A="85920" B="VARIACION FRANQUICIA (RC.PROF.)" />
<ROW A="85925" B="VARIACION FRANQUICIA (RC.VANT)" />
<ROW A="86000" B="PROFESION-ESPECIALIDAD(SALUD)" />
<ROW A="86100" B="DESCUENTO CANTIDAD(SOLO COLECTIVAS)" />
<ROW A="86150" B="DESCUENTO CANTIDAD(SOLO COLECTIVAS RC PROD.)" />
<ROW A="86200" B="REPOSICION SUMA ASEG.(RC.GRAL)" />
<ROW A="86300" B="REPOSICION SUMA ASEG.(RC.PROF)" />
<ROW A="86310" B="REPOSICION SUMA ASEG.(DYO)" />
<ROW A="86400" B="CUBRE CONTAMINACION SUBITA Y ACCIDENTAL" />
<ROW A="86500" B="CANTIDAD DE CONSORCIOS ADMINISTRADOS" />
<ROW A="86510" B="CANT.TOTAL DE UNIDADES FUNCIONALES" />
<ROW A="86520" B="ZONA DE RIESGO (ADM.CONSORCIOS)" />
<ROW A="86530" B="CANTIDAD CONSORCIOS ASEGURADOS EN FP" />
<ROW A="86540" B="TIPO DE REGISTRO (ADM.CONSORCIOS)" />
<ROW A="86550" B="NRO. DE REGISTRO (ADM.CONSORCIOS)" />
<ROW A="86600" B="DISTRITO - PROVINCIA" />
<ROW A="86610" B="CANTIDAD DE ACTUACIONES NOTARIALES" />
<ROW A="86620" B="CARGO" />
<ROW A="86630" B="N° DE REGISTRO NOTARIAL" />
<ROW A="86640" B="DOMICILIO REGISTRO NOTARIAL" />
<ROW A="86690" B="ESPECIALIZACION PERITO" />
<ROW A="86700" B="ESPECIALIZACION SINDICATURA CONCURSAL" />
<ROW A="86710" B="CANTIDAD DE CLIENTES" />
<ROW A="86720" B="JURISDICCION" />
<ROW A="86730" B="RC CONDUCCION DE DEPENDIENTES DEL ASEGURADO" />
<ROW A="86735" B="COB. GUARDA Y/O DEPOSITO DE VEHICULOS" />
<ROW A="86740" B="CUBRE TRABAJOS EN RECINTOS DE TERCEROS" />
<ROW A="86750" B="CUBRE DAÑOS CAUSADOS POR VEHICULOS DE TERCEROS" />
<ROW A="86760" B="ADICIONAL SUMINISTRO DE ALIMENTOS" />
<ROW A="86770" B="CUBRE TRASLADO MAQ. FUERA DEL PREDIO" />
<ROW A="87000" B="ACTIVIDAD (CIIU)" />
<ROW A="87010" B="ACTIVIDAD DE LA EMPRESA (CIIU)" />
<ROW A="87020" B="GRUPO RC AMBIENTAL" />
<ROW A="87100" B="SALARIO" />
<ROW A="87110" B="HORAS TRABAJADAS" />
<ROW A="87200" B="ZONA DE RIESGO" />
<ROW A="87300" B="EXPERIENCIA SINIESTRAL" />
<ROW A="87400" B="SUMA ASEGURADA" />
<ROW A="87500" B="UBICACION DE LA OBRA" />
<ROW A="87600" B="CARACTERISTICA DE LA OBRA" />
<ROW A="87700" B="TIPO DE OBRA" />
<ROW A="87800" B="TIPO DE OBRA" />
<ROW A="87810" B="LUGAR DE LA OBRA" />
<ROW A="87820" B="CANTIDAD DE PLANTAS A CONST./REFACC." />
<ROW A="87830" B="SUPERFICIE A CONST./REFACC." />
<ROW A="87840" B="OBRA INICIADA" />
<ROW A="87850" B="LA OBRA POSEE CERRAMIENTOS" />
<ROW A="87860" B="EXISTENCIA DE INMUEBLES LINDEROS" />
<ROW A="87870" B="ANTIGÜEDAD DE INMUEBLES LINDEROS" />
<ROW A="87880" B="CANTIDAD DE PLANTAS DE INMUEBLES LINDEROS" />
<ROW A="87890" B="CANTIDAD DE PLANTAS A DEMOLER" />
<ROW A="87900" B="SUPERFICIE A DEMOLER" />
<ROW A="87901" B="ZONA DE RIESGO" />
<ROW A="87910" B="ACTIVIDAD R.C. COMPRENSIVA" />
<ROW A="87920" B="ACTIVIDAD R.C. COMPRENSIVA" />
<ROW A="87930" B="ACTIVIDAD RC. COMPRENSIVA" />
<ROW A="87940" B="COB. PRODUCTOS-FACT.ESTIM." />
<ROW A="87950" B="COB. MAQ/EQ.CONST.Y MONTAJE-CANTIDAD" />
<ROW A="87960" B="COB. PLANTA DE GAS LICUADO-TONELAJE" />
<ROW A="87970" B="COB. ANTENAS/MÁSTILES-UBICACIÓN" />
<ROW A="87980" B="COB. CARGA TRANSPORTADA-TIPO DE PRODUCTO" />
<ROW A="87990" B="CUBRE TENDIDO CABLES VÍA PÚBLICA(SIN SUM. DE ENERGÍA ELECT.)" />
<ROW A="88000" B="FACTURACION EST. DE LA ACT." />
<ROW A="88010" B="FACTURACIÓN EST. DE LA ACT. EN PESOS" />
<ROW A="88020" B="TIPO DE VANT" />
<ROW A="88021" B="USO" />
<ROW A="88022" B="ADICIONAL COMPETENCIAS DEP., RECREATIVAS Y ACROBÁTICAS" />
<ROW A="88023" B="ACTIVIDAD RIESGOS CIBERNETICOS" />
<ROW A="88024" B="ACTIVIDAD RC PUERTOS Y TERMINALES" />
<ROW A="90000" B="OCUPACION" />
<ROW A="90001" B="CATEGORIA DE RIESGO" />
<ROW A="90100" B="CLASE DE EQUIPO" />
<ROW A="90101" B="CLASE DE EQUIPO DE  CONTRATISTA" />
<ROW A="90110" B="CLASE DE EQUIPO ELECTRONICO" />
<ROW A="90200" B="IDENTIFICACION DEL EQUIPO" />
<ROW A="90201" B="IDENTIFICACION DEL EQUIPO DE CONTRATISTA" />
<ROW A="90210" B="IDENTIFICACION DEL EQUIPO ELECTR." />
<ROW A="90300" B="DISPOSICION DEL EQUIPO" />
<ROW A="90350" B="COB.EQUIPO PORTATIL EN EL EXTERIOR" />
<ROW A="90400" B="DESCUENTO CANT MAQUINAS" />
<ROW A="90500" B="TIPO DE MAQUINA" />
<ROW A="90550" B="TIPO DE MAQUINARIA" />
<ROW A="90560" B="ADIC.INCENDIO-ROBO-FEN.NATURALES" />
<ROW A="90600" B="MARCA-MODELO DE MAQUINA" />
<ROW A="90610" B="TIPO-DESCRIPCIÓN" />
<ROW A="90620" B="MARCA" />
<ROW A="90630" B="MODELO" />
<ROW A="90640" B="PATENTE/N° DE INSCRIPCIÓN" />
<ROW A="90650" B="N° DE SERIE/CHASIS/MOTOR" />
<ROW A="90700" B="NRO. SERIE O MOTOR" />
<ROW A="90800" B="AÑO" />
<ROW A="90810" B="AÑO" />
<ROW A="90900" B="CONDUCTOR" />
<ROW A="90950" B="RASTREADOR VEHICULAR" />
<ROW A="90960" B="SUMA ASEGURADA TOTAL $" />
<ROW A="90965" B="SUMA ASEGURADA TOTAL $" />
<ROW A="90970" B="CLASE EQUIPO" />
<ROW A="90975" B="ACTIVIDAD EQ.ELECTR. ASEGURA2" />
<ROW A="90980" B="CANTIDAD DE MODULOS" />
<ROW A="90990" B="RESP. CIVIL CRUZADA" />
<ROW A="90991" B="CUBRE RC BIENES BAJO CONTROL Y CUSTODIA" />
<ROW A="90992" B="POSEE PÓLIZA VIGENTE DE GRANIZO EN FED.PAT." />
<ROW A="90993" B="CUBRE RC CONTAMINACION SUBITA Y ACCIDENTAL" />
<ROW A="91000" B="TIPO DE OBRA" />
<ROW A="91100" B="ZONA DE RIESGO" />
<ROW A="91110" B="GRUPO" />
<ROW A="91115" B="TIPO DE RIESGO" />
<ROW A="91116" B="TIPO DE RIESGO" />
<ROW A="91120" B="VIGENCIA PERIODO CONSTRUCCION" />
<ROW A="91125" B="VIGENCIA PERIODO CONST./ MONTAJE" />
<ROW A="91130" B="TIPO DE OBRA" />
<ROW A="92000" B="VARIACION FRANQUICIA" />
<ROW A="93000" B="TIPO DE OBRA" />
<ROW A="93010" B="HUELGA, MOTÍN, CONMOCIÓN CIVIL" />
<ROW A="93020" B="LUGAR/CARACTERISTICA DE LA OBRA" />
<ROW A="93030" B="RIESGO SISMICO (AMPARO B)" />
<ROW A="93040" B="CLICLON INUNDACION (AMPARO C)" />
<ROW A="93050" B="ERROR DE DISEÑO" />
<ROW A="93060" B="PERIODO DE MANTENIMIENTO" />
<ROW A="93080" B="PERIODO DE PRUEBAS" />
<ROW A="93100" B="RC COMBINADO (AMPARO E Y F)" />
<ROW A="93120" B="CLASE DE MAQ. DE CONST./MONTAJE" />
<ROW A="93130" B="ZONA (MAQ. DE CONST./MONTAJE)" />
<ROW A="93140" B="CUBRE TRANSPORTE TERRESTRE EN VEHÍCULOS DE TERCEROS" />
<ROW A="94000" B="AJUSTE AUTOMATICO SUMA ASEG." />
<ROW A="95000" B="ESTUDIO LIQUIDADOR" />
<ROW A="95001" B="FECHA INFORME LIQUIDACION" />
<ROW A="99001" B="LLAVE" />
<ROW A="99002" B="DERIVADO 1" />
<ROW A="99003" B="DERIVADO 2" />
<ROW A="100010" B="PROVINCIAS" />
<ROW A="100020" B="PARTIDO" />
<ROW A="100025" B="LOCALIDADES GRANIZO" />
<ROW A="100026" B="PARTIDO DTO" />
<ROW A="100030" B="CULTIVO" />
<ROW A="100040" B="FECHA VENCIMIENTO" />
<ROW A="100050" B="NRO. DE HECTAREAS" />
<ROW A="100055" B="NRO. DE HECT. AFECTADAS" />
<ROW A="100060" B="NRO. DE QUINTALES" />
<ROW A="100065" B="NRO. DE QUNT. AFECTADOS" />
<ROW A="100070" B="NRO. DE LOTES" />
<ROW A="100072" B="NRO. DE LOTES AFECTADOS" />
<ROW A="100075" B="MONEDA O QUINTALES" />
<ROW A="100080" B="CULTIVOS" />
<ROW A="100082" B="SOLICITA SELF" />
<ROW A="100085" B="SUPERFICIE LOTE O AREA" />
<ROW A="100090" B="VALOR DEL QUINTAL" />
<ROW A="100100" B="GRUPOS DE LOCALIDADES" />
<ROW A="100150" B="COORDENADAS GPS LATITUD SUR" />
<ROW A="100160" B="COORDENADAS GPS LONGITUD W" />
<ROW A="100200" B="FRANQUICIA OPTATIVA" />
<ROW A="100220" B="FRANQUICIA OBLIGATORIA" />
<ROW A="100250" B="ANEXOS" />
<ROW A="100300" B="CONTRATOS" />
<ROW A="100400" B="COTIZA PREMIO" />
<ROW A="100500" B="VALOR POR HECTAREA" />
<ROW A="100550" B="VALOR EN EMERGENCIA" />
<ROW A="100580" B="PORCENTAJE DE DAÑO" />
<ROW A="100585" B="PORCENTAJE DE COINCIDENCIA (IA)" />
<ROW A="100590" B="SUMA ASEG. AFECTADA" />
<ROW A="100600" B="QUINTALES POR HECTAREA" />
<ROW A="100700" B="ADICIONAL HELADA" />
<ROW A="100720" B="DESC. CONTRAT. TEMPRANA" />
<ROW A="100750" B="ZONAS - HELADA" />
<ROW A="100755" B="FRANQ. HELADA" />
<ROW A="100800" B="ADICIONAL VIENTO" />
<ROW A="100850" B="ZONAS - VIENTO" />
<ROW A="100855" B="FRANQ. VIENTO" />
<ROW A="100900" B="ADICIONAL LLUVIA EXCESIVA" />
<ROW A="100910" B="BONIF. POR BONO" />
<ROW A="100920" B="NUMERO DE BONO" />
<ROW A="100950" B="ZONAS - LLUVIA EXCESIVA" />
<ROW A="100955" B="FRANQ. LLUVIA EXCESIVA" />
<ROW A="100980" B="ZONAS - FALTA DE PISO" />
<ROW A="100985" B="FRANQ. FALTA DE PISO" />
<ROW A="100990" B="ADICIONAL VIENTO-TRIGO" />
<ROW A="100995" B="NRO. SOLICITUD" />
<ROW A="100998" B="NOMBRE DE ESTABLECIMIENTO" />
<ROW A="101000" B="PORC DAÑO 1" />
<ROW A="101010" B="PORC DAÑO 2" />
<ROW A="101020" B="PORC DAÑO 3" />
<ROW A="101030" B="PORC DAÑO 4" />
<ROW A="101040" B="PORC DAÑO 5" />
<ROW A="101050" B="PORC DAÑO 6" />
<ROW A="101060" B="PORC DAÑO 7" />
<ROW A="101070" B="PORC DAÑO 8" />
<ROW A="101080" B="PORC DAÑO 9" />
<ROW A="101090" B="PORC DAÑO 10" />
<ROW A="101100" B="VALOR EMERG. 1" />
<ROW A="101110" B="VALOR EMERG. 2" />
<ROW A="101120" B="VALOR EMERG. 3" />
<ROW A="101130" B="VALOR EMERG. 4" />
<ROW A="101140" B="VALOR EMERG. 5" />
<ROW A="101150" B="VALOR EMERG. 6" />
<ROW A="101160" B="VALOR EMERG. 7" />
<ROW A="101170" B="VALOR EMERG. 8" />
<ROW A="101180" B="VALOR EMERG. 9" />
<ROW A="101190" B="VALOR EMERG. 10" />
<ROW A="101200" B="NOMBRE CONTACTO" />
<ROW A="101210" B="TELEFONO DEL CONCTATO" />
<ROW A="101220" B="TELEFONO ALTERNATIVO PRODUCTOR" />
<ROW A="101230" B="DECLINADO" />
<ROW A="101240" B="DESISTIDO" />
<ROW A="120001" B="CATEGORIA DE RIESGO" />
<ROW A="120002" B="OCUPACION" />
<ROW A="120003" B="TIPO RIESGO" />
<ROW A="120004" B="USO DE MOTOCICLETAS IN ITINERE" />
<ROW A="120005" B="PRACTICA DEP. CLA. (3)" />
<ROW A="120006" B="PRACTICA OTROS DEP." />
<ROW A="120007" B="PLAN A CUBRIR" />
<ROW A="120008" B="TIPO DE TRANSPORTE" />
<ROW A="120009" B="NIVELES" />
<ROW A="120010" B="RESP.CIVIL ESCOLARES" />
<ROW A="120011" B="CAMPO DE DEPORTES" />
<ROW A="120012" B="TRANSPORTE EN OMNIBUS" />
<ROW A="120013" B="COLONIA DE VACACIONES" />
<ROW A="120014" B="DEPORTES" />
<ROW A="120015" B="NIVELES" />
<ROW A="120016" B="ADICIONAL VIAJES" />
<ROW A="120017" B="TIPO DE MOTOCICLETA" />
<ROW A="120018" B="AP TERCERA EDAD" />
<ROW A="120019" B="AP CICLISTAS" />
<ROW A="120020" B="FRANQ. A. MED.FARM.$" />
<ROW A="120021" B="TIPO DE CLIENTE" />
<ROW A="120022" B="ACCIDENTAL MOTOCICLISTAS" />
<ROW A="120025" B="TIPO DE ENSE?ANZA" />
<ROW A="120026" B="ACTIVIDAD PERMITIDA EN VENTA WEB" />
<ROW A="120030" B="CLAU. 13-PLURALIDAD DE SEGUROS" />
<ROW A="120040" B="LIMITE INDEM. POR ACONTECIMIENTO" />
<ROW A="120050" B="LIMITE MAXIMO INDEMNIZATORIO" />
<ROW A="120070" B="MARCA DEL VEHICULO" />
<ROW A="120075" B="MODELO" />
<ROW A="120080" B="PATENTE" />
<ROW A="120085" B="AÑO" />
<ROW A="120087" B="NUMERO DE CHASIS" />
<ROW A="120090" B="NUMERO DE MOTOR" />
<ROW A="120095" B="CANTIDAD DE PLAZAS" />
<ROW A="120099" B="LOCALIDAD DE RESIDENCIA" />
<ROW A="120100" B="CAUSANTE" />
<ROW A="120200" B="NOMBRE ACCIDENTADO" />
<ROW A="120300" B="BENEFICIARIO" />
<ROW A="120350" B="ACC. PERS. MICROSEGUROS" />
<ROW A="120400" B="FECHA NAC.FALLECIDO" />
<ROW A="120401" B="FECHA INICIO VIAJE" />
<ROW A="120402" B="FECHA FIN VIAJE" />
<ROW A="120403" B="CANTIDAD DE PERSONAS" />
<ROW A="120404" B="CANTIDAD DE CAPITAS" />
<ROW A="120405" B="FECHA INICIO EXCURSION" />
<ROW A="120406" B="FECHA FIN EXCURSION" />
<ROW A="120500" B="INDIVIDUAL O COLECTIVA" />
<ROW A="120600" B="NOMBRE BENEFICIARIO" />
<ROW A="120700" B="NRO. POLIZA PRINCIPAL" />
<ROW A="120800" B="CLAUSULA DE NO REPETICION" />
<ROW A="120850" B="EMPRESA 1" />
<ROW A="120851" B="EMPRESA 2" />
<ROW A="120852" B="EMPRESA 3" />
<ROW A="120900" B="OCUPACION NO PERMITIDA" />
<ROW A="120950" B="OPCION DE SUMA ASEGURADA" />
<ROW A="120960" B="CANTIDAD DE PERSONAS" />
<ROW A="120970" B="CANTIDAD CAPITAS - T. ESTUDIANTIL" />
<ROW A="120971" B="PLAN TURISMO ESTUDIANTIL" />
<ROW A="120972" B="CANTIDAD CAPITAS - T. ALTERNATIVO" />
<ROW A="120973" B="PLAN TURISMO ALTERNATIVO" />
<ROW A="120974" B="OCUPACIÓN ADICIONAL (SUJETO AUTORIZACION DE LA SECCION)" />
<ROW A="130001" B="USO CAUCION" />
<ROW A="130002" B="RIESGO CUBIERTO" />
<ROW A="130010" B="IMPORTADOR EXPORTADOR" />
<ROW A="130020" B="REGISTRO IMPORT/EXPORT" />
<ROW A="130030" B="DOMICILIO IMPORT/EXPORT" />
<ROW A="130040" B="CUIT IMPORT/EXPORT" />
<ROW A="130050" B="DESPACHANTE DE ADUANA" />
<ROW A="130060" B="REGISTRO DESP. DE ADUANA" />
<ROW A="130070" B="DOMICILIO DESP. DE ADUANA" />
<ROW A="130080" B="CUIT DESP. DE ADUANA" />
<ROW A="130086" B="PRIMA DER ENDOSO" />
<ROW A="130090" B="PRIMA MODIFICADA" />
<ROW A="130100" B="PERIODO" />
<ROW A="130150" B="TURISMO ESTUDIANTIL" />
<ROW A="130200" B="GARANTIAS ADUANERAS" />
<ROW A="130210" B="ADM. DE SOCIEDADES" />
<ROW A="130220" B="EJER. ACTIV. Y/O PROFESION" />
<ROW A="130230" B="NRO. DE CONTRATO" />
<ROW A="130240" B="COD. DE SEGURIDAD" />
<ROW A="130241" B="FECHA SALIDA CONTINGENTE" />
<ROW A="130242" B="DETALLES LEGALES" />
<ROW A="130243" B="TEXTO ENDOSO" />
<ROW A="130244" B="DES. COMERCIAL" />
<ROW A="130245" B="LEGAJO" />
<ROW A="130246" B="PERMISO PRECARIO" />
<ROW A="130247" B="EMAIL CONSTITUIDO" />
<ROW A="130250" B="AGENTES DE LOTERIA" />
<ROW A="130300" B="SECRETARIA ENERGIA" />
<ROW A="130310" B="DAÑO AMBIENTAL" />
<ROW A="130350" B="SUM.Y/O SERV. PRIVADO" />
<ROW A="130400" B="SUM.Y/O SERV. PUBLICO" />
<ROW A="130450" B="OBRA PRIVADA" />
<ROW A="130500" B="OBRA PUBLICA" />
<ROW A="130550" B="TRANSP. AUTOMOTOR" />
<ROW A="130600" B="SISTEMA DE GNC" />
<ROW A="130650" B="EMP. VIAJES Y TURISMO" />
<ROW A="130700" B="GARANTIA DE ALQUILERES" />
<ROW A="130750" B="CONCESIONES" />
<ROW A="130800" B="GARANTIAS JUDICIALES" />
<ROW A="130900" B="CONTRATO DE LEASING" />
<ROW A="130910" B="MUESTRA EL DATO" />
<ROW A="130995" B="ADMINISTRADORES DE CONSORCIO" />
<ROW A="170000" B="CAUSANTE" />
<ROW A="170050" B="CANTIDAD DE PERSONAS" />
<ROW A="170100" B="NOMBRE FALLECIDO" />
<ROW A="170200" B="NOMBRE BENEFICIARIO" />
<ROW A="170300" B="FECHA DE NACIMIENTO" />
<ROW A="170340" B="FECHA DE INGRESO" />
<ROW A="170350" B="CAUSA TRAUMATICA" />
<ROW A="170400" B="CAUSA NO TRAUMATICA" />
<ROW A="170450" B="CARENCIA" />
<ROW A="170500" B="ENFERMEDADES PREEXISTENTES" />
<ROW A="170550" B="DECLARACION DE SALUD" />
<ROW A="170600" B="EXAMEN MEDICO" />
<ROW A="170650" B="INFORMACION EN SUSCRIPCION" />
<ROW A="170900" B="ACTIVIDAD" />
<ROW A="180001" B="F. NAC. ASEGURADO" />
<ROW A="180002" B="PARENTESCO ADIC. 1" />
<ROW A="180003" B="RECARGOS" />
<ROW A="180004" B="PARENTESCO ADIC. 2" />
<ROW A="180005" B="F. NAC. ADICIONAL 1" />
<ROW A="180006" B="PARENTESCO ADIC. 3" />
<ROW A="180007" B="F. NAC. ADICIONAL 2" />
<ROW A="180008" B="DESCUENTO ACTIVIDAD" />
<ROW A="180009" B="F. NAC. ADICIONAL 3" />
<ROW A="180010" B="OCUPACION" />
<ROW A="180011" B="ASEGURADO PRINCIPAL" />
<ROW A="180012" B="CODIGO DE CONVENIO" />
<ROW A="180013" B="CONYUGE" />
<ROW A="180014" B="CANTIDAD DE HIJOS" />
<ROW A="180015" B="CARACTER DEL ASEGURADO" />
<ROW A="180016" B="CANTIDAD DE MODULOS (LCT)" />
<ROW A="180020" B="ASEGURADO ADICIONAL 1" />
<ROW A="180030" B="ASEGURADO ADICIONAL 2" />
<ROW A="180040" B="ASEGURADO ADICIONAL 3" />
<ROW A="180041" B="TIPO DE SEGURO" />
<ROW A="180042" B="RELACION DEL GRUPO" />
<ROW A="180043" B="ASEGURABLES" />
<ROW A="180044" B="ESTRUCTURA DE CAPITALES" />
<ROW A="180045" B="F. INGRESO AL TRABAJO" />
<ROW A="180048" B="SALARIO" />
<ROW A="180050" B="CAUSANTE" />
<ROW A="180100" B="NOMBRE ACCIDENTADO" />
<ROW A="180140" B="EDAD PROMEDIO" />
<ROW A="180141" B="TIPO DE OPERACION" />
<ROW A="180145" B="NRO PRESTAMO" />
<ROW A="180160" B="CANTIDAD DE MODULOS" />
<ROW A="180170" B="EDAD ASEGURADO TITULAR" />
<ROW A="180171" B="NOMBRE ASEGURADO ADICIONAL" />
<ROW A="180172" B="DNI ASEGURADO ADICIONAL" />
<ROW A="180173" B="EDAD ASEGURADO ADICIONAL" />
<ROW A="180174" B="BENEFICIARIO DEL ASEG. ADICIONAL" />
<ROW A="180180" B="CARÁCTER ASEGURADO" />
<ROW A="180185" B="N° LEGAJO" />
<ROW A="180190" B="CANTIDAD DE MÓDULOS AFINIDAD" />
<ROW A="180200" B="NOMBRE BENEFICIARIO" />
<ROW A="180300" B="FECHA DE NAC.FALLECIDO" />
<ROW A="180400" B="NRO. DE PRODUCTOR" />
<ROW A="180450" B="CONVENIOS COLECTIVOS" />
<ROW A="180500" B="CICLO ESCOLAR" />
<ROW A="180600" B="VALORES POR CICLO" />
<ROW A="180650" B="REQUISITO DE ASEGURABILIDAD" />
<ROW A="180700" B="EDAD LIMITE DE INGRESO" />
<ROW A="180750" B="EDAD DE REDUC. AL 50% DE CAPITAL" />
<ROW A="180755" B="EDAD MAXIMA DE PERMANENCIA" />
<ROW A="180800" B="EDAD LIMITE DE PERMANENCIA" />
<ROW A="180850" B="PORC. MINIMO DE ADHESION" />
<ROW A="180900" B="TIPO DE INVALIDEZ" />
<ROW A="180920" B="TIPO DE ADICIONAL POR ACC." />
<ROW A="180930" B="TIPO DE ENFERMEDAD GRAVE" />
<ROW A="180940" B="TIPO DE TRANSPLANTE" />
<ROW A="180950" B="TIPO DE RENTA POR INTERNACION" />
<ROW A="180960" B="CANTIDAD DE PERSONAS" />
<ROW A="180970" B="TIPO DE EMPLEADO" />
<ROW A="180980" B="PLAN PROD 180130" />
<ROW A="190003" B="RECARGO POR EST. DE SALUD" />
<ROW A="190006" B="EDAD AL INICIO" />
<ROW A="190010" B="FECHA DE NACIMIENTO" />
<ROW A="190020" B="SEXO" />
<ROW A="190030" B="FUMADOR" />
<ROW A="190040" B="OCUPACION" />
<ROW A="190050" B="DEPORTE" />
<ROW A="190060" B="PLAZO CARENCIA Y LIMITE ANUAL" />
<ROW A="190070" B="SALUD" />
<ROW A="190080" B="EDAD HIJO 1" />
<ROW A="190090" B="EDAD HIJO 2" />
<ROW A="190100" B="EDAD HIJO 3" />
<ROW A="190110" B="BENEFICIO POR FALLECIMIENTO" />
<ROW A="190120" B="EDAD HIJO 4" />
<ROW A="190130" B="EDAD HIJO 5" />
<ROW A="190140" B="EDAD HIJO 6" />
<ROW A="190150" B="MODULOS" />
<ROW A="190160" B="EDAD ASEGURADO" />
<ROW A="190170" B="PLAZO EN AÑOS" />
<ROW A="190180" B="MODULOS VIDA INTEGRAL" />
<ROW A="190181" B="BENEFICIARIO" />
<ROW A="190190" B="% ACT. SUMA ASEGURADA:" />
<ROW A="193600" B="PESO (KG)" />
<ROW A="193601" B="ESTATURA (MTS)" />
<ROW A="193602" B="¿PADECE / PADECIÓ ALGUNA ENFERMEDAD? (ULTIMOS 5 AÑOS)" />
<ROW A="193603" B="¿SE ENCUENTRA BAJO TRATAMIENTO MÉDICO?" />
<ROW A="220001" B="TIPO DE EMBARCACION" />
<ROW A="220002" B="ANTIGUEDAD" />
<ROW A="220003" B="TIPO CONSTRUCCION" />
<ROW A="220004" B="ROTURA DE PALO EN REGATA" />
<ROW A="220005" B="INCENDIO EN GUARDERIA" />
<ROW A="220006" B="RC INCENDIO, PERSONAS Y COSAS" />
<ROW A="220007" B="TRANSPORTE EN TRAILER ANUAL" />
<ROW A="220008" B="AMPL. A NAVEGACION OCEANICA" />
<ROW A="220009" B="NAV. COSTERA HASTA FLORIANOPOLIS" />
<ROW A="220010" B="HUELGA VANDALISMO" />
<ROW A="220011" B="ROBO EN EL AGUA" />
<ROW A="220012" B="CODIGO DE RIESGO" />
<ROW A="220013" B="NOMBRE DE EMBARCACION" />
<ROW A="220014" B="NUMERO DE MATRICULA" />
<ROW A="220015" B="BANDERA" />
<ROW A="220016" B="ASTILLERO" />
<ROW A="220017" B="A?O DE CONSTRUCCION" />
<ROW A="220018" B="ESLORA" />
<ROW A="220019" B="MANGA" />
<ROW A="220020" B="PUNTAL" />
<ROW A="220021" B="TONELAJE BRUTO" />
<ROW A="220022" B="TONELAJE NETO" />
<ROW A="220023" B="PRIMER MOTOR MARCA" />
<ROW A="220024" B="PRIMER MOTOR TIPO" />
<ROW A="220025" B="PRIMER MOTOR POTENCIA" />
<ROW A="220026" B="SEGUNDO MOTOR MARCA" />
<ROW A="220027" B="SEGUNDO MOTOR TIPO" />
<ROW A="220028" B="SEGUNDO MOTOR POTENCIA" />
<ROW A="220029" B="ZONA DE NAVEGACION" />
<ROW A="220030" B="ZONA DE NAVEGACION POR MAR" />
<ROW A="220031" B="MODELO MOTO/JET" />
<ROW A="220032" B="LUGAR GUARDA" />
<ROW A="220035" B="TIPO DE MOTO DE AGUA" />
<ROW A="220036" B="ANTIGUEDAD MOTO" />
<ROW A="220040" B="CLAUSULAS" />
<ROW A="220050" B="NRO. DE REGISTRO NAC. DE BUQUES" />
<ROW A="220060" B="GUARDA O AMARRE" />
<ROW A="220061" B="LUGAR GUARDA O AMARRE" />
<ROW A="220062" B="CUIT GUARDA O AMARRE" />
<ROW A="220065" B="NAVEGA POR DELTA DEL PARANA ?" />
<ROW A="220070" B="ASISTENCIA MECANICA" />
<ROW A="220080" B="TEMPORAL E INUNDACION" />
<ROW A="220090" B="BUEN RESULTADO" />
<ROW A="220091" B="TIPO DE KAYAK" />
<ROW A="220100" B="CANTIDAD DE ASIENTOS" />
<ROW A="220120" B="ROBO JET SKY" />
<ROW A="220130" B="RC GASES Y LIQUIDOS" />
<ROW A="220140" B="RC PRACTICA DE DEPORTES" />
<ROW A="220150" B="VALOR ACCESORIOS" />
<ROW A="220160" B="VALOR CASCO" />
<ROW A="220170" B="VALOR MOTOR" />
<ROW A="220180" B="VALOR VELAS" />
<ROW A="220190" B="RC PRACTICA DEPORTES ACUATICOS" />
<ROW A="220200" B="ACCIDENTE  PERSONALES" />
<ROW A="220210" B="EFECTOS PERSONALES" />
<ROW A="220301" B="TIPO DE EMBARCACION" />
<ROW A="220302" B="ANTIGUEDAD" />
<ROW A="220303" B="TIPO DE CONSTRUCCION" />
<ROW A="220400" B="TIPO DE BUQUE" />
<ROW A="220401" B="ANTIGUEDAD" />
<ROW A="240000" B="PROPIEDAD DEL/ LOS EQUIPOS" />
<ROW A="240001" B="UBICACION POR ZONA DE RIESGO" />
<ROW A="240002" B="TIPO DE VIVIENDA" />
<ROW A="240003" B="DISYUNTOR" />
<ROW A="240004" B="ALARMA" />
<ROW A="240005" B="PUERTA BLINDADA" />
<ROW A="240006" B="VIGILANCIA PERMANENTE" />
<ROW A="240007" B="BUEN RESULTADO" />
<ROW A="240008" B="LINDEROS: BALDIO, OBRA, EDIF. ABANDO" />
<ROW A="240009" B="EN COMUNIC. COMERCIO O SIMILAR" />
<ROW A="240010" B="HURACAN-VENDAVAL-CICLON-TORNADO" />
<ROW A="240011" B="USO DE LA VIVIENDA" />
<ROW A="240012" B="ADICIONALES RC: PISCINAS, FILTRACIONES, DAÑOS A INM. VECINOS" />
<ROW A="240013" B="TIPO DE CONSTRUCCION EXTERIOR" />
<ROW A="240014" B="TERREMOTO (INCENDIO)" />
<ROW A="240015" B="REPOSICION A NUEVO - COB. 070" />
<ROW A="240016" B="DAÑOS POR TENSION" />
<ROW A="240017" B="SUBLIMITE ROBO DINERO EN EFECTIVO" />
<ROW A="240018" B="TERREMOTO (DAÑOS)" />
<ROW A="240019" B="DAÑOS POR GRANIZO" />
<ROW A="240020" B="CALIDAD DE LA CONSTRUCCION" />
<ROW A="240021" B="TIPO DE TECHO" />
<ROW A="240022" B="LOCALIDAD DEL RIESGO" />
<ROW A="240025" B="RECONSTRUC. A NUEVO EDIFICIO" />
<ROW A="240026" B="TIPO DE CLIENTE" />
<ROW A="240030" B="METROS CUBIERTOS (APROX.)" />
<ROW A="240031" B="PACK CON EL AUTO" />
<ROW A="240035" B="REGIMEN DE OCUPACION" />
<ROW A="240036" B="CASERO" />
<ROW A="240037" B="POLIZA OTROS RAMOS" />
<ROW A="240040" B="ESTADO DE LOS EQUIPOS" />
<ROW A="240050" B="COMB FLIAR ZONA A" />
<ROW A="240051" B="COMB FLIAR ZONA B" />
<ROW A="240060" B="ZONA INCENDIO" />
<ROW A="240061" B="ZONA TERREMOTO" />
<ROW A="240062" B="ZONA DAÑOS" />
<ROW A="240063" B="ZONA ROBO" />
<ROW A="240064" B="DAÑOS POR DERRUMBE" />
<ROW A="240065" B="INUNDACION COB. 070-075-080" />
<ROW A="240068" B="PERMANENCIA (EN MESES)" />
<ROW A="240069" B="SINIESTROS PAGADOS (ULT. 36 MESES)" />
<ROW A="250000" B="UBICACION ZONA DE RIESGO" />
<ROW A="250001" B="ALARMA CONTRA ROBO" />
<ROW A="250002" B="PROTECCION ABERTURAS AL FRENTE" />
<ROW A="250003" B="VIGILANCIA NOCTURNA" />
<ROW A="250004" B="COMUNIC. CON VIVIENDA DEL ASEG." />
<ROW A="250005" B="PLANTA COMUNICADA CON ADMINIST." />
<ROW A="250006" B="UBICACION DEL RIESGO" />
<ROW A="250007" B="PROTECCION ELECTRICA" />
<ROW A="250008" B="TIPO DE TECHOS" />
<ROW A="250009" B="HURACAN-CICLON-TORNADO AL EDIFICIO" />
<ROW A="250010" B="DAÑOS POR GRANIZO" />
<ROW A="250011" B="ADICIONALES RC (ALIMENTOS)" />
<ROW A="250012" B="DAÑOS POR TENSION (COB 140-145)" />
<ROW A="250013" B="TERREMOTO (INCENDIO)" />
<ROW A="250014" B="HURACAN-CICLON-TORNADO AL CONTENIDO" />
<ROW A="250015" B="TERREMOTO (DAÑOS)" />
<ROW A="250016" B="ROBO 1º RIESG RELATIVO - RELACION" />
<ROW A="250017" B="COLOR-ACTIVIDAD" />
<ROW A="250018" B="ARTICULO TARIFA" />
<ROW A="250019" B="PERDIDA DE FRIO MERCADERIAS" />
<ROW A="250020" B="ADICIONALES RC (CARTELES)" />
<ROW A="250021" B="ADICIONALES RC (ASCENSORES)" />
<ROW A="250022" B="ADICIONALES RC (CALDERAS)" />
<ROW A="250023" B="ADICIONALES RC (EXCURSIONES)" />
<ROW A="250024" B="ADICIONALES RC (PILETA)" />
<ROW A="250025" B="CLASIFICACION DEL CONTENIDO" />
<ROW A="250030" B="BUEN RESULTADO" />
<ROW A="250031" B="ADICIONALES RC (CONTRATISTAS)" />
<ROW A="250032" B="ADICIONALES RC (ANIMALES)" />
<ROW A="250033" B="ADICIONALES RC (VIGILANCIA)" />
<ROW A="250034" B="RC NUMERO DE UBICACIONES" />
<ROW A="250035" B="INSTALACIONES CONTRA INCENDIO" />
<ROW A="250036" B="PERSONAL DE SEGURIDAD" />
<ROW A="250037" B="FRANQUICIA PARA VALORES" />
<ROW A="250038" B="REPOSICION DE SUMAS" />
<ROW A="250039" B="MEDIDAS DE SEGURIDAD" />
<ROW A="250900" B="DOCUMENTACION" />
<ROW A="260000" B="PROPIEDAD" />
<ROW A="260005" B="TIPO DE VIVIENDA" />
<ROW A="260010" B="STOCK-OCUPACION" />
<ROW A="260020" B="LINDEROS" />
<ROW A="260030" B="ZONA-UBICACION" />
<ROW A="260035" B="CALIDAD DE LA CONSTRUCCION" />
<ROW A="260040" B="ORDEN Y LIMPIEZA" />
<ROW A="260050" B="PROHIBIDO FUMAR" />
<ROW A="260060" B="CALEFACCION" />
<ROW A="260070" B="CANTIDAD DE PLANTAS" />
<ROW A="260080" B="PLANTAS OCUP.P/ASEG" />
<ROW A="260090" B="SUP.CUBIERTAS M2" />
<ROW A="260100" B="TIPO DE CONSTRUCCION" />
<ROW A="260110" B="PAREDES EXTERIOR" />
<ROW A="260120" B="TECHOS" />
<ROW A="260130" B="PISOS" />
<ROW A="260135" B="ANTIGUEDAD DEL EDIFICIO" />
<ROW A="260140" B="ENTREPISOS" />
<ROW A="260145" B="LIMPIEZA" />
<ROW A="260150" B="ESCALERAS" />
<ROW A="260155" B="MANTENIMIENTO" />
<ROW A="260160" B="DIVISIONES INTERIORES" />
<ROW A="260165" B="ESTIBA MERCADERIAS" />
<ROW A="260167" B="TIPO DE MERCADERIA" />
<ROW A="260170" B="ASCENSORES" />
<ROW A="260175" B="CARGA DE FUEGO" />
<ROW A="260180" B="MONTACARGAS" />
<ROW A="260185" B="SEÑALIZACION-CIRCULACION" />
<ROW A="260190" B="CALDERAS" />
<ROW A="260195" B="CLASIFICACION MERCADERIAS" />
<ROW A="260200" B="CABLEADO ILUMINACION" />
<ROW A="260210" B="CABLEADO FUERZA MOTRIZ" />
<ROW A="260220" B="PUESTA A TIERRA" />
<ROW A="260230" B="DISYUNTOR" />
<ROW A="260240" B="LLAVES TERMICAS" />
<ROW A="260250" B="PARARRAYOS" />
<ROW A="260260" B="ESTADO DE LA INSTALACION" />
<ROW A="260265" B="CORTE ENERGIA AL FINALIZAR JORN." />
<ROW A="260270" B="CANT.MATAFUEGOS" />
<ROW A="260280" B="ACCESO MATAFUEGOS" />
<ROW A="260290" B="ESTADO MATAFUEGOS" />
<ROW A="260300" B="VENCIM. MATAFUEGOS" />
<ROW A="260310" B="CUBRE NECESIDAD ACT." />
<ROW A="260320" B="HIDRANTES" />
<ROW A="260330" B="EXIST. PERS. ENTRENADO" />
<ROW A="260335" B="PORTERO" />
<ROW A="260340" B="CANT. PERS. ENTRENADO" />
<ROW A="260350" B="GRADO DE CAPACITACION" />
<ROW A="260360" B="EXIST. SERENO" />
<ROW A="260370" B="CANT. SERENO" />
<ROW A="260380" B="EXIST. VIGILANCIA" />
<ROW A="260390" B="CANT. VIGILANCIA" />
<ROW A="260400" B="DETECCION AUTOMATICA" />
<ROW A="260410" B="BOMBEROS-DISTANCIA-KMS" />
<ROW A="260420" B="ADICIONALES" />
<ROW A="260425" B="SPRINKLERS" />
<ROW A="260430" B="H.V.C.T" />
<ROW A="260435" B="PROTECCION LUMINARIAS" />
<ROW A="260440" B="GRANIZO" />
<ROW A="260445" B="VIGILANCIA Y SERENO" />
<ROW A="260450" B="PERD. POR STRO. EN PORC." />
<ROW A="260460" B="PREDIO" />
<ROW A="260470" B="VENTANAS FRENTE" />
<ROW A="260471" B="VENTANAS LATERAL" />
<ROW A="260472" B="VENTANAS FONDO" />
<ROW A="260480" B="CORT METALICAS MALLA FR" />
<ROW A="260481" B="CORT METALICA MALLA LAT" />
<ROW A="260482" B="CORT METALICA MALLA FONDO" />
<ROW A="260483" B="CORT METALICA ENTERA FR" />
<ROW A="260484" B="CORT METALICA ENTERA LAT" />
<ROW A="260485" B="CORT METALICA ENTERA FONDO" />
<ROW A="260486" B="VIDRIER., VENT., ABERT. AL FRENTE" />
<ROW A="260487" B="VIDRIER., VENT., ABERT. LATERAL" />
<ROW A="260488" B="VIDRIER., VENT., ABERT. AL FONDO" />
<ROW A="260490" B="CLARABOYAS,BANDEROLA FRENTE" />
<ROW A="260500" B="CLARABOYA,BANDEROLA LATERAL" />
<ROW A="260501" B="CLARABOYA,BANDEROLA FONDO" />
<ROW A="260502" B="CLARABOYA,BANDEROLA TECHO" />
<ROW A="260505" B="PUERTA BLINDADA" />
<ROW A="260510" B="CERRADURAS FRENTE" />
<ROW A="260511" B="CERRADURAS LATERALES" />
<ROW A="260512" B="CERRADURAS FONDO" />
<ROW A="260520" B="CERRADURAS" />
<ROW A="260525" B="VIGILANCIA-TIPO" />
<ROW A="260526" B="VIGILANCIA EXTERNA" />
<ROW A="260527" B="SERENO" />
<ROW A="260530" B="ALARMAS" />
<ROW A="260540" B="FORMA DE AVISO" />
<ROW A="260550" B="TIPO DE ALARMA" />
<ROW A="260560" B="CAJA FUERTE" />
<ROW A="260561" B="CAJA FUERTE EMPOTRADA" />
<ROW A="260562" B="CERRADURA CAJA FUERTE" />
<ROW A="260565" B="PRESENCIA POLICIAL" />
<ROW A="260570" B="SINIESTROS" />
<ROW A="260575" B="ATENCION AL PUBLICO" />
<ROW A="260580" B="¿TODAS LAS PIEZAS SE ENCUENT.SANAS?" />
<ROW A="260582" B="CANT. DE PIEZAS PAÑOS FIJOS" />
<ROW A="260584" B="MEDIDAS PAÑOS FIJOS" />
<ROW A="260585" B="CANTIDAD DE PIEZAS ROTAS" />
<ROW A="260586" B="CANT. DE PIEZAS PAÑOS MOVILES" />
<ROW A="260587" B="CANTIDAD DE PIEZAS ROTAS" />
<ROW A="260588" B="MEDIDAS PAÑOS MOVILES" />
<ROW A="260590" B="CANT. DE PIEZAS" />
<ROW A="260595" B="VIDRIOS AL FRENTE" />
<ROW A="260600" B="MEDIDAS DE PIEZAS" />
<ROW A="260605" B="VIDRIOS CONTRAFRENTE" />
<ROW A="260610" B="RESULTADO DE LA INSPECCION" />
<ROW A="260655" B="ACCESO A LOS FONDOS" />
<ROW A="261000" B="CANTIDAD DE SINIESTROS" />
<ROW A="270000" B="CIELORRASOS" />
<ROW A="270100" B="USO DE LA VIVIENDA" />
<ROW A="270200" B="EDIFICADO MEDIANERA A MEDIANERA" />
<ROW A="270300" B="HABILITACION" />
<ROW A="270310" B="COCHERAS" />
<ROW A="270320" B="CAPACIDAD VEHICULOS" />
<ROW A="270330" B="CANT. ELEVADORES VEHICULOS" />
<ROW A="270340" B="CONTROL DOCUM. PATENTES" />
<ROW A="270350" B="LLAVES LOCAL SUMINIST. AL CLIENTE" />
<ROW A="270360" B="LLAVES DEL VEHICULO" />
<ROW A="270370" B="POSEE CAMAS PARA INTERNACIÓN" />
<ROW A="270380" B="CAMAS PARA INTERNACIÓN" />
<ROW A="270390" B="POSEE QUIROFANO" />
<ROW A="270400" B="QUIROFANOS" />
<ROW A="270410" B="CAPACIDAD MÁX DE ESPECTADORES" />
<ROW A="270440" B="CARTELES/LETREROS" />
<ROW A="270450" B="ASCENSORES" />
<ROW A="270460" B="CALDERAS" />
<ROW A="280000" B="TIPO DE INSPECCION" />
<ROW A="280010" B="DISPOSICION DEL EQUIPO" />
<ROW A="280020" B="SISTEMA DE RASTREO" />
<ROW A="280030" B="CONTACTO CON PRODUCTOS" />
<ROW A="280040" B="ESTADO DE LOS EQUIPOS" />
<ROW A="300000" B="CALIFICACION DEL JUICIO" />
<ROW A="300100" B="CALIFICACION  SERV. TERCEROS" />
<ROW A="300150" B="CALIFICACION DEL SINIESTRO" />
<ROW A="300200" B="MOTIVO DE LA DEMANDA" />
<ROW A="300250" B="RANGOS DE INCAPACIDAD" />
<ROW A="300300" B="ESTADO ADMINISTRATIVO" />
<ROW A="300400" B="RECLAMO INGRESADO" />
<ROW A="300500" B="CLASIFICACION DOCUMENTOS" />
<ROW A="300520" B="CARACTERISTICA DEL DOCUMENTO" />
<ROW A="300530" B="DESTINO" />
<ROW A="370005" B="CARACTER DE ASEG." />
<ROW A="370010" B="FECHA DE NACIMIENTO" />
<ROW A="370012" B="ZONA DE RIESGO" />
<ROW A="370013" B="MODALIDAD DE COBERTURA" />
<ROW A="370014" B="TIPO DE SERVICIO" />
<ROW A="370015" B="FACTOR AJUSTE RIESGO" />
<ROW A="370016" B="RECARGO DE SEGURIDAD" />
<ROW A="370018" B="MODALIDAD Y TIPO DE SERVICIO" />
<ROW A="370020" B="CANTIDAD DE TITULARES" />
<ROW A="370030" B="CONYUGES" />
<ROW A="370040" B="HIJOS POR TITULAR" />
<ROW A="370050" B="PADRES POR TITULAR" />
<ROW A="370060" B="PADRES POL. POR TIT." />
<ROW A="370160" B="EDAD ASEGURADO" />
<ROW A="400000" B="CANT MODULOS SUMA ASEG" />
<ROW A="460486" B="VIDRIER., VENT., ABERT. AL FRENTE" />
<ROW A="460487" B="VIDRIER., VENT., ABERT. LATERAL" />
<ROW A="460488" B="VIDRIER., VENT., ABERT. AL FONDO" />
<ROW A="500000" B="GRUPO DE DATOS" />
<ROW A="600000" B="FEC. DE ACEPTACION" />
<ROW A="600010" B="NRO. POLIZA DE LA CEDENTE" />
<ROW A="600100" B="ACTIV. DEL DEMANDANTE" />
<ROW A="600120" B="COB.MEDICA DEL DEMANDANTE" />
<ROW A="600140" B="TIPO DE INCAPACIDAD" />
<ROW A="600150" B="INGRESOS DEL DEMANDANTE" />
<ROW A="600170" B="JUSTIPRECIO" />
<ROW A="600180" B="PRESUPUESTO" />
<ROW A="600190" B="EDAD" />
<ROW A="600200" B="USO - DESTINO DEL VEH." />
<ROW A="600210" B="P. MEC. DAÑO EMERGENTE" />
<ROW A="600220" B="P. MEC. PRIVACION USO" />
<ROW A="600230" B="P. MEC. DESVALORIZACION" />
<ROW A="600240" B="P. LUCRO CESANTE" />
<ROW A="600250" B="ULT. MONTO PRETENDIDO" />
<ROW A="600260" B="FECHA REG. MTO. PRETENDIDO" />
<ROW A="600270" B="ULT. OFRECIMIENTO" />
<ROW A="600280" B="FECHA REG. ULT. OFRECIMIENTO" />
<ROW A="610000" B="CODIGO PREMIOS A PRODUCTORES" />
<ROW A="700001" B="DIAGNOSTICOS DE LA OMS" />
<ROW A="700002" B="NIVEL DE GRAVEDAD" />
<ROW A="700003" B="AGENTE CAUSANTE" />
<ROW A="700004" B="PARTE DEL CUERPO AFECTADA" />
<ROW A="700005" B="NATURALEZA" />
<ROW A="700006" B="OCUPACION" />
<ROW A="700007" B="TIPO DE SINIESTRO" />
<ROW A="700008" B="TIPO DE TRASLADO" />
<ROW A="700009" B="CAUSA DEL SINIESTRO" />
<ROW A="700010" B="MODULOS" />
<ROW A="700011" B="TIPO DE ALTA" />
<ROW A="700013" B="ENTE HOMOLOGADOR" />
<ROW A="700014" B="TIPO DE INCAPACIDAD" />
<ROW A="700015" B="CARACTER INCAPACIDAD" />
<ROW A="700016" B="GRADO INCAPACIDAD" />
<ROW A="700018" B="COMISION MEDICA" />
<ROW A="700100" B="ACTIVIDADES DE AFIP" />
<ROW A="700102" B="SECTOR" />
<ROW A="700103" B="FORMA DE ACCIDENTE" />
<ROW A="700106" B="LUGAR DE ACCIDENTE" />
<ROW A="700107" B="LUGAR DE ENVIO" />
<ROW A="700108" B="ESTADO TRAMITE JUNTA MEDICA" />
<ROW A="700109" B="TIPO DE EXAMEN" />
<ROW A="700110" B="CODIGO DE EXAMEN" />
<ROW A="700111" B="ESTADO DEL SINIESTRO" />
<ROW A="700112" B="GRUPOS DE MODULOS" />
<ROW A="700113" B="ESTADO DEL TRAMITE INCAPACIDAD" />
<ROW A="700201" B="CANTIDAD DE DIAS" />
<ROW A="700202" B="NIVEL DE GRAVEDAD - SRT" />
<ROW A="700204" B="ZONA DEL CUERPO AFECTADA - SRT" />
<ROW A="700205" B="DIAGNOSTICO PARA EL CAP" />
<ROW A="700206" B="PORCENTAJE DE INCAPACIDAD" />
<ROW A="700207" B="H.G.95" />
<ROW A="700208" B="H.G.57" />
<ROW A="700209" B="H.G.63" />
<ROW A="700210" B="H.G.92" />
<ROW A="700211" B="INTERNACION" />
<ROW A="700212" B="FKT" />
<ROW A="700213" B="VISITAS_MEDICAS" />
<ROW A="700214" B="ORTESIS" />
<ROW A="700215" B="SEGUIMIENTO PRIORITARIO" />
<ROW A="700216" B="CANTIDAD DE TRASLADOS" />
<ROW A="700217" B="COD. ENFERMEDAD UART" />
<ROW A="700218" B="DIAS DE BAJA" />
<ROW A="700219" B="DIAGNOSTICO CASO MUERTE" />
<ROW A="700906" B="FUNCION DE LA OCUPACION" />
<ROW A="800001" B="DEMANDA ORIGINAL" />
<ROW A="800010" B="PORCENTAJE ADICIONAL" />
<ROW A="800020" B="FECHA DE ACT. BASE" />
<ROW A="800030" B="FECHA DE VIG. DESDE" />
<ROW A="800040" B="NRO. DE COLUMNA (SSN)" />
<ROW A="800050" B="FECHA DE ULT. MODIFICACION" />
<ROW A="800060" B="ACCIDENTE O ENFERMEDAD" />
<ROW A="800100" B="ACTIVIDAD" />
<ROW A="800110" B="GRUPO ACTIVIDAD" />
<ROW A="800120" B="ACTIVIDAD ANTERIOR" />
<ROW A="800130" B="ACTIVIDAD NUEVA" />
<ROW A="800140" B="ACTIVIDAD REVISION 4" />
<ROW A="800145" B="ES CIIU REVISION 4?" />
<ROW A="800150" B="ACTIV. SECUNDARIA" />
<ROW A="800160" B="RESCINDIDA DE OTRA ART" />
<ROW A="800170" B="TRASPASO" />
<ROW A="800171" B="EMPLEADOR PAGA ILT" />
<ROW A="800172" B="¿EL EMPLEADOR TIENE UN UNICO ESTABLECIMIENTO?" />
<ROW A="800180" B="RELACION CIIU4 A CIIU3" />
<ROW A="800200" B="NIVEL" />
<ROW A="800250" B="PROGRAMA ALTA SINIESTRALIDAD" />
<ROW A="800300" B="CANTIDAD DE EMPLEADOS" />
<ROW A="800400" B="COTIZA PREMIO" />
<ROW A="800500" B="PORC. DE COMISION" />
<ROW A="800700" B="AGENTES DE RIESGO" />
<ROW A="800701" B="CANCERIGENO" />
<ROW A="800702" B="FEC_DE_CANCER" />
<ROW A="800703" B="FEC_HA_CANCER" />
<ROW A="800704" B="USUARIO_CANCER" />
<ROW A="800710" B="EXAMENES PERIODICOS" />
<ROW A="800800" B="TERMINACION CUIT" />
<ROW A="800810" B="AÑO FACTURACION ART" />
<ROW A="800820" B="MES FACTURACION ART" />
<ROW A="800830" B="FECHA VENC. INTERES ART" />
<ROW A="800840" B="DEF. DE IMPORTES FIJOS" />
<ROW A="800900" B="ANEXO II" />
<ROW A="800901" B="ANEXO III" />
<ROW A="800950" B="MTO. ESTIMADO DE RECLAMO" />
<ROW A="800960" B="NOMBRE PERITO OFICIAL" />
<ROW A="800970" B="FREQ. DIAS HAS. 5" />
<ROW A="800980" B="FREQ. DIAS HAS. 9" />
<ROW A="800990" B="FREQ. DIAS MAS DE 10" />
<ROW A="801000" B="COBRO INDEM. POR ART?" />
<ROW A="801100" B="INCAPACIDAD RECLAMADA" />
<ROW A="801200" B="INDEM. EST. POR L.24557" />
<ROW A="810100" B="GRUPO PREVENCION" />
<ROW A="810150" B="PASADO A PREVENCION DE ART" />
<ROW A="810200" B="VENTANILLA ELECTRONICA" />
<ROW A="810300" B="ACTIVIDAD NO PERMITIDA" />
<ROW A="810310" B="PRESENTACION ESTUDIOS MEDICOS" />
<ROW A="810320" B="PRESENTACION CERTIF. MEDICOS" />
<ROW A="810330" B="MEDICO PARTE ACTORA 1" />
<ROW A="810340" B="MEDICO PARTE ACTORA 2" />
<ROW A="810350" B="PERITO OFICIAL MEDICO" />
<ROW A="810360" B="PERITO OFICIAL PSICOLOGO" />
<ROW A="810370" B="PERITO OFICIAL OTROS" />
<ROW A="810380" B="PORC. INCAP. SEGUN MEDICO" />
<ROW A="810390" B="PORC. INCAP. SEGUN PSICOLOGO" />
<ROW A="810400" B="PORC. INCAP. SEGUN OTROS" />
<ROW A="810410" B="ARTE REVISO AL SINIESTRADO" />
<ROW A="810420" B="ACTUACION DE LA ART" />
<ROW A="810430" B="PORC. INCAP. SEGUN ART" />
<ROW A="810440" B="RIESGO PARA PLA/FT" />
<ROW A="810450" B="TASA DE REFERENCIA" />
<ROW A="810460" B="TASA DE COMPETENCIA" />
<ROW A="849300" B="COEF. ADM A PRIMA OR" />
<ROW A="900000" B="PROVINCIA" />
<ROW A="900001" B="ZONA DE RIESGO" />
<ROW A="900002" B="LOCALIDAD" />
<ROW A="900003" B="DESCUENTO PRIM/COMISION" />
<ROW A="900004" B="DESC. DEL RIESGO" />
<ROW A="900005" B="DESCUENTO COMISION" />
<ROW A="900006" B="DESCUENTO PRIMA" />
<ROW A="900007" B="COLECTIVO" />
<ROW A="900008" B="TIPO DE TRANSACCION" />
<ROW A="900010" B="RIESGO" />
<ROW A="900015" B="DINAMICO" />
<ROW A="900016" B="TIPO DE FACTURACION" />
<ROW A="900020" B="TP COBERTURA" />
<ROW A="900030" B="ACTIVIDAD" />
<ROW A="900040" B="REFACTURAR" />
<ROW A="900045" B="RAZON SOCIAL" />
<ROW A="900050" B="PARTIDOS" />
<ROW A="900060" B="VIDA INICIAL" />
<ROW A="900070" B="MONEDA" />
<ROW A="900080" B="AGENCIA" />
<ROW A="900090" B="NRO.PRODUCTOR" />
<ROW A="900100" B="TIPO DE EQUIPOS" />
<ROW A="900200" B="MARCAS DE EQUIPOS" />
<ROW A="900300" B="OTROS DEPART. JUDICIALES" />
<ROW A="900400" B="ESTADO CIVIL" />
<ROW A="900500" B="INDICADORES LAVADO" />
<ROW A="900501" B="SEGMENTO CLIENTES LAVADO" />
<ROW A="900502" B="RIESGO PLA/FT" />
<ROW A="900503" B="PROBABILIDAD" />
<ROW A="900504" B="IMPACTO" />
<ROW A="900505" B="RANGO IMPACTO" />
<ROW A="900510" B="PERFIL TRANSACCIONAL" />
<ROW A="900511" B="LEGAJO CLIENTE" />
<ROW A="900512" B="PRODUCTOS ADQUIRIDOS" />
<ROW A="900520" B="DATOS RES UIF 230" />
<ROW A="900530" B="NACIONALIDAD" />
<ROW A="900531" B="NACIONALIDAD CLIENTE" />
<ROW A="900540" B="LOCALIDAD LIMITROFE" />
<ROW A="900550" B="PEP" />
<ROW A="900560" B="CASCOS" />
<ROW A="900570" B="VIDA CON AHORRO" />
<ROW A="900580" B="RETIRO" />
<ROW A="900590" B="GRANIZO" />
<ROW A="900600" B="RANGOS PRIMA LAVADO" />
<ROW A="900610" B="CAUCION" />
<ROW A="900620" B="MAYOR $200.000 / PERS FISICA" />
<ROW A="900630" B="MAYOR $200.000 / COND IVA" />
<ROW A="900640" B="PERSONA SOSPECHOSA" />
<ROW A="900650" B="REPORTE UIF" />
<ROW A="900660" B="ANTIGUEDAD CLIENTE" />
<ROW A="900670" B="CANAL DE VENTA" />
<ROW A="900680" B="VEHICULOS ALTA GAMA" />
<ROW A="900690" B="DOMICILIO LIMITROFE" />
<ROW A="900691" B="PROVINCIA CLIENTE" />
<ROW A="900700" B="RANGOS CANT. OPER. LAVADO" />
<ROW A="900800" B="CUMP. INFO. SOLICITADA LAVADO" />
<ROW A="900810" B="PRIMERO O TODOS" />
<ROW A="900820" B="OPCIONES COD VARIABLE" />
<ROW A="900900" B="VERIF. INFO. SOLICIDADA LAVADO" />
<ROW A="900950" B="COEF. POR PRODUCTOR" />
<ROW A="900951" B="COEF. DESCUENTO PRIMA ADMINISTRATIVA" />
<ROW A="900952" B="GARAGE CUARENTENA" />
<ROW A="900960" B="PLAN AJUSTE DE CARTERA" />
<ROW A="901000" B="EMPRESAS ASEGURADORAS" />
<ROW A="910000" B="PLAN" />
<ROW A="915000" B="DESC  ANEXOS 1" />
<ROW A="950100" B="ZONA RIESGO" />
<ROW A="950150" B="DERIVACION MEDIACIONES" />
<ROW A="950200" B="MARCA DE ACCESORIOS" />
<ROW A="960001" B="POLIZAS DE OTROS RIESGOS VIGENTES" />
<ROW A="960002" B="BONIFICACION POR BUEN RESULTADO" />
<ROW A="960003" B="MEDIDAS DE SEGURIDAD" />
<ROW A="960004" B="CON POLIZA DE SEGURO TECNICO" />
<ROW A="960005" B="BONIFICACION POR BUEN RESULTADO" />
<ROW A="960006" B="TIPO DE MAQUINARIA" />
<ROW A="960007" B="DISTANCIA." />
<ROW A="960008" B="MUERTE POR ASFIXIA" />
<ROW A="960009" B="APERTURA DE BOQUILLAS" />
<ROW A="990000" B="PRODUCTOS EXCLUIDOS CAMBIO MATRICULA" />
<ROW A="990001" B="CON SINIESTROS" />
<ROW A="990002" B="CUBRE CRISTALES PLANTA ALTA" />
</ROWDATA>
</DATAPACKET>
